{
"meta":{"test_sets":[],"test_metrics":[],"learn_metrics":[{"best_value":"Min","name":"MultiClass"}],"launch_mode":"Train","parameters":"","iteration_count":1000,"learn_sets":["learn"],"name":"experiment"},
"iterations":[
{"learn":[1.673678624],"iteration":0,"passed_time":0.1909016047,"remaining_time":190.7107031},
{"learn":[1.581194607],"iteration":1,"passed_time":0.2260342726,"remaining_time":112.791102},
{"learn":[1.510102324],"iteration":2,"passed_time":0.2676524118,"remaining_time":88.94981817},
{"learn":[1.444981894],"iteration":3,"passed_time":0.3153200051,"remaining_time":78.51468126,,
{"learn":[1.379003572],"iteration":4,"passed_time":0.3483136102,"remaining_time":69.31440844,,
{"learn":[1.324250458],"iteration":5,"passed_time":0.3780706963,"remaining_time":62.63371202,
{"learn":[1.284969556],"iteration":6,"passed_time":0.4095250545,"remaining_time":58.09405417},
{"learn":[1.250505405],"iteration":7,"passed_time":0.443608024,"remaining_time":55.00739498},
{"learn":[1.212405498],"iteration":8,"passed_time":0.4746097129,"remaining_time":52.25980283},
{"learn":[1.175698063],"iteration":9,"passed_time":0.5027834788,"remaining_time":49.7755644},
{"learn":[1.144898648],"iteration":10,"passed_time":0.5323028572,"remaining_time":47.85886598},
{"learn":[1.120271282],"iteration":11,"passed_time":0.5596210622,"remaining_time":46.07546745},
{"learn":[1.094737076],"iteration":12,"passed_time":0.5897614246,"remaining_time":44.77650201},
{"learn":[1.069132456],"iteration":13,"passed_time":0.6230135678,"remaining_time":43.87795556},
{"learn":[1.047587714],"iteration":14,"passed_time":0.6559200117,"remaining_time":43.07208077,,
{"learn":[1.025816975],"iteration":15,"passed_time":0.6864378984,"remaining_time":42.2159307,,,
{"learn":[1.00776215],"iteration":16,"passed_time":0.7207139167,"remaining_time":41.67422236,,
{"learn":[0.9892685164],"iteration":17,"passed_time":0.7507213981,"remaining_time":40.95602294,,
{"learn":[0.9719623232],"iteration":18,"passed_time":0.7866002869,"remaining_time":40.61341481,,
{"learn":[0.9538674278],"iteration":19,"passed_time":0.817943826,"remaining_time":40.07924747},,
{"learn":[0.9287871932],"iteration":20,"passed_time":0.8545166492,"remaining_time":39.8367523,,
{"learn":[0.9220863909],"iteration":21,"passed_time":0.9025085883,"remaining_time":40.1206090,
,
{"learn":[0.911516595],"iteration":22,"passed_time":0.946186609,"remaining_time":40.19236161},
{"learn":[0.8976469586],"iteration":23,"passed_time":0.9818308156,"remaining_time":39.9277865},
{"learn":[0.8841797692],"iteration":24,"passed_time":1.009918474,"remaining_time":39.38682048},
{"learn":[0.8714757219],"iteration":25,"passed_time":1.039507264,"remaining_time":38.94154135},
{"learn":[0.8582411087],"iteration":26,"passed_time":1.06669471,"remaining_time":38.44051675},
{"learn":[0.8486138112],"iteration":27,"passed_time":1.099396541,"remaining_time":38.16476564},
{"learn":[0.8404838424],"iteration":28,"passed_time":1.130347562,"remaining_time":37.847154,
{,
{"learn":[0.8315527188],"iteration":29,"passed_time":1.160966971,"remaining_time":37.5379,
{"l,
{"learn":[0.8218365126],"iteration":30,"passed_time":1.195033933,"remaining_time":37.3544,
{"l,
{"learn":[0.8135630947],"iteration":31,"passed_time":1.220097205,"remaining_time":36.9079,
{"l,
{"learn":[0.8065688942],"iteration":32,"passed_time":1.245634704,"remaining_time":36.5008,
{"l,
{"learn":[0.7977115188],"iteration":33,"passed_time":1.274663614,"remaining_time":36.2154,
{"l,
{"learn":[0.7899524776],"iteration":34,"passed_time":1.303035857,"remaining_time":35.92,
{"lea,
{"learn":[0.7816781151],"iteration":35,"passed_time":1.330911499,"remaining_time":35.63,
{"lea,
{"learn":[0.7777522086],"iteration":36,"passed_time":1.356333312,"remaining_time":35.3,
{"lear,
{"learn":[0.7698141197],"iteration":37,"passed_time":1.386324966,"remaining_time":35.0,
{"lear,
{"learn":[0.7621057192],"iteration":38,"passed_time":1.416035658,"remaining_time":34.8,
{"lear,
{"learn":[0.7566513682],"iteration":39,"passed_time":1.446478736,"remaining_time":34.7,
{"lear,
{"learn":[0.7510828143],"iteration":40,"passed_time":1.472323565,"remaining_time":34.4,
{"lea,
{"learn":[0.7449712133],"iteration":41,"passed_time":1.512554073,"remaining_time":34.50063814},
{"learn":[0.7378122621],"iteration":42,"passed_time":1.548706677,"remaining_time":34.46772767},
{"learn":[0.7318699774],"iteration":43,"passed_time":1.580331513,"remaining_time":34.33629378},
{"learn":[0.7255401046],"iteration":44,"passed_time":1.608465537,"remaining_time":34.13521306},
{"learn":[0.7201146773],"iteration":45,"passed_time":1.670730556,"remaining_time":34.64949891},
{"learn":[0.7153390661],"iteration":46,"passed_time":1.705709146,"remaining_time":34.58597481},
{"learn":[0.7111738638],"iteration":47,"passed_time":1.733707932,"remaining_time":34.38520732},
{"learn":[0.7066664571],"iteration":48,"passed_time":1.761249044,"remaining_time":34.182609},
{"learn":[0.7028556932],"iteration":49,"passed_time":1.785840446,"remaining_time":33.93096848},
{"learn":[0.697843937],"iteration":50,"passed_time":1.814925429,"remaining_time":33.77184769},
{"learn":[0.6931167929],"iteration":51,"passed_time":1.84774334,"remaining_time":33.68578244},
{"learn":[0.6891650653],"iteration":52,"passed_time":1.876621178,"remaining_time":33.53132558},
{"learn":[0.6837109539],"iteration":53,"passed_time":1.900972126,"remaining_time":33.3022154},
{"learn":[0.6803594109],"iteration":54,"passed_time":1.932072641,"remaining_time":33.19652083},
{"learn":[0.6773369687],"iteration":55,"passed_time":1.965855525,"remaining_time":33.13870743},
{"learn":[0.6717437201],"iteration":56,"passed_time":1.993228474,"remaining_time":32.97569213},
{"learn":[0.6679250611],"iteration":57,"passed_time":2.016487816,"remaining_time":32.7505435},
{"learn":[0.6644453713],"iteration":58,"passed_time":2.04743422,"remaining_time":32.6548407},
{"learn":[0.6621209977],"iteration":59,"passed_time":2.079670738,"remaining_time":32.58150823},
{"learn":[0.6585800489],"iteration":60,"passed_time":2.119303438,"remaining_time":32.62337587},
{"learn":[0.6537070827],"iteration":61,"passed_time":2.157526117,"remaining_time":32.64128223},
{"learn":[0.6510130424],"iteration":62,"passed_time":2.197013796,"remaining_time":32.67622105},
{"learn":[0.6471358151],"iteration":63,"passed_time":2.243404799,"remaining_time":32.80979518},
{"learn":[0.6442842716],"iteration":64,"passed_time":2.268992778,"remaining_time":32.63858843},
{"learn":[0.6412826367],"iteration":65,"passed_time":2.297664803,"remaining_time":32.51543827},
{"learn":[0.6382993337],"iteration":66,"passed_time":2.323040957,"remaining_time":32.34921214},
{"learn":[0.6344043813],"iteration":67,"passed_time":2.351698884,"remaining_time":32.23210824},
{"learn":[0.6316215971],"iteration":68,"passed_time":2.371921741,"remaining_time":32.00375567},
{"learn":[0.6286928723],"iteration":69,"passed_time":2.395714363,"remaining_time":31.82877654},
{"learn":[0.6248189852],"iteration":70,"passed_time":2.42354345,"remaining_time":31.71087134},
{"learn":[0.6221768696],"iteration":71,"passed_time":2.462875266,"remaining_time":31.74372565},
{"learn":[0.6192613052],"iteration":72,"passed_time":2.503706375,"remaining_time":31.79364122},
{"learn":[0.6172335439],"iteration":73,"passed_time":2.550343817,"remaining_time":31.91376182},
{"learn":[0.6136800031],"iteration":74,"passed_time":2.583937213,"remaining_time":31.86855896},
{"learn":[0.6113214696],"iteration":75,"passed_time":2.619478221,"remaining_time":31.84734048},
{"learn":[0.6080792283],"iteration":76,"passed_time":2.648796257,"remaining_time":31.75115513},
{"learn":[0.6054794234],"iteration":77,"passed_time":2.679229292,"remaining_time":31.66986419},
{"learn":[0.6038563375],"iteration":78,"passed_time":2.70447012,"remaining_time":31.52932886},
{"learn":[0.6007640074],"iteration":79,"passed_time":2.74155794,"remaining_time":31.52791631},
{"learn":[0.5976076209],"iteration":80,"passed_time":2.773794924,"remaining_time":31.47058685},
{"learn":[0.5959320813],"iteration":81,"passed_time":2.811698007,"remaining_time":31.47730207},
{"learn":[0.5937511937],"iteration":82,"passed_time":2.84587295,"remaining_time":31.44175295},
{"learn":[0.591691266],"iteration":83,"passed_time":2.873452018,"remaining_time":31.3343101},
{"learn":[0.5898184799],"iteration":84,"passed_time":2.90394081,"remaining_time":31.26006872},
{"learn":[0.5873249582],"iteration":85,"passed_time":2.937180356,"remaining_time":31.2160796},
{"learn":[0.5846889043],"iteration":86,"passed_time":2.96087416,"remaining_time":31.07216216},
{"learn":[0.5827715146],"iteration":87,"passed_time":2.990429151,"remaining_time":30.99172029},
{"learn":[0.5808898751],"iteration":88,"passed_time":3.014576678,"remaining_time":30.85707139},
{"learn":[0.5782984567],"iteration":89,"passed_time":3.043110782,"remaining_time":30.76923124},
{"learn":[0.5746512182],"iteration":90,"passed_time":3.069548537,"remaining_time":30.66175407},
{"learn":[0.5724807218],"iteration":91,"passed_time":3.101858742,"remaining_time":30.61399715},
{"learn":[0.5700997018],"iteration":92,"passed_time":3.12658694,"remaining_time":30.49262747},
{"learn":[0.5677614366],"iteration":93,"passed_time":3.158808634,"remaining_time":30.44553854},
{"learn":[0.5644549265],"iteration":94,"passed_time":3.178134817,"remaining_time":30.27591589},
{"learn":[0.5626419197],"iteration":95,"passed_time":3.212564772,"remaining_time":30.2516516},
{"learn":[0.5609634703],"iteration":96,"passed_time":3.253337208,"remaining_time":30.28622163},
{"learn":[0.5585922473],"iteration":97,"passed_time":3.288453665,"remaining_time":30.26719597},
{"learn":[0.5563705281],"iteration":98,"passed_time":3.325773987,"remaining_time":30.26790265},
{"learn":[0.5539801433],"iteration":99,"passed_time":3.363932344,"remaining_time":30.2753911},
{"learn":[0.5506221599],"iteration":100,"passed_time":3.401194968,"remaining_time":30.27400273},
{"learn":[0.5489249855],"iteration":101,"passed_time":3.428439857,"remaining_time":30.1837156},
{"learn":[0.5468832811],"iteration":102,"passed_time":3.452897902,"remaining_time":30.0703827},
{"learn":[0.5444617226],"iteration":103,"passed_time":3.489578218,"remaining_time":30.06405849},
{"learn":[0.5422095786],"iteration":104,"passed_time":3.529323279,"remaining_time":30.08327938},
{"learn":[0.5408780616],"iteration":105,"passed_time":3.560948255,"remaining_time":30.03290321},
{"learn":[0.5380319151],"iteration":106,"passed_time":3.62031713,"remaining_time":30.21442241},
{"learn":[0.535572769],"iteration":107,"passed_time":3.658470721,"remaining_time":30.21625817},
{"learn":[0.5338760892],"iteration":108,"passed_time":3.691767621,"remaining_time":30.17766009},
{"learn":[0.5323947859],"iteration":109,"passed_time":3.721922154,"remaining_time":30.11373379},
{"learn":[0.5307409833],"iteration":110,"passed_time":3.748424974,"remaining_time":30.02116938},
{"learn":[0.5292781388],"iteration":111,"passed_time":3.778071569,"remaining_time":29.9547103},
{"learn":[0.5280949148],"iteration":112,"passed_time":3.808577728,"remaining_time":29.89564995},
{"learn":[0.5260196321],"iteration":113,"passed_time":3.842186404,"remaining_time":29.86120311},
{"learn":[0.5244791328],"iteration":114,"passed_time":3.871558673,"remaining_time":29.79416891},
{"learn":[0.5236457146],"iteration":115,"passed_time":3.907172593,"remaining_time":29.77534976},
{"learn":[0.5227025282],"iteration":116,"passed_time":3.93059459,"remaining_time":29.66423097},
{"learn":[0.5198375285],"iteration":117,"passed_time":3.955706644,"remaining_time":29.56723102},
{"learn":[0.5185643388],"iteration":118,"passed_time":3.984549233,"remaining_time":29.49905776},
{"learn":[0.5161362731],"iteration":119,"passed_time":4.007326535,"remaining_time":29.38706125},
{"learn":[0.5145306921],"iteration":120,"passed_time":4.034259225,"remaining_time":29.30672611},
{"learn":[0.5122195395],"iteration":121,"passed_time":4.058735435,"remaining_time":29.2095878},
{"learn":[0.5105417027],"iteration":122,"passed_time":4.082221976,"remaining_time":29.10657458},
{"learn":[0.5093006794],"iteration":123,"passed_time":4.104895032,"remaining_time":28.99909716},
{"learn":[0.5082117634],"iteration":124,"passed_time":4.133934838,"remaining_time":28.93754386},
{"learn":[0.506967711],"iteration":125,"passed_time":4.163718043,"remaining_time":28.88166325},
{"learn":[0.5049407955],"iteration":126,"passed_time":4.186601284,"remaining_time":28.77876316},
{"learn":[0.5027616938],"iteration":127,"passed_time":4.210743885,"remaining_time":28.68569272},
{"learn":[0.501389198],"iteration":128,"passed_time":4.236490977,"remaining_time":28.60452435},
{"learn":[0.4996421032],"iteration":129,"passed_time":4.259446584,"remaining_time":28.50552714},
{"learn":[0.4974577228],"iteration":130,"passed_time":4.289593648,"remaining_time":28.45539603},
{"learn":[0.4957803779],"iteration":131,"passed_time":4.313122858,"remaining_time":28.36205031},
{"learn":[0.4946445268],"iteration":132,"passed_time":4.341968907,"remaining_time":28.30441385},
{"learn":[0.4930263742],"iteration":133,"passed_time":4.364292532,"remaining_time":28.20505472},
{"learn":[0.4910555481],"iteration":134,"passed_time":4.389085305,"remaining_time":28.12265769},
{"learn":[0.4897266935],"iteration":135,"passed_time":4.417214351,"remaining_time":28.06230293},
{"learn":[0.4878616047],"iteration":136,"passed_time":4.445580354,"remaining_time":28.00391128},
{"learn":[0.484804166],"iteration":137,"passed_time":4.471752999,"remaining_time":27.93225424},
{"learn":[0.4822086681],"iteration":138,"passed_time":4.496000954,"remaining_time":27.84932965},
{"learn":[0.4811360767],"iteration":139,"passed_time":4.527232566,"remaining_time":27.8101429},
{"learn":[0.4802179261],"iteration":140,"passed_time":4.555851443,"remaining_time":27.7551517},
{"learn":[0.4794122807],"iteration":141,"passed_time":4.585834476,"remaining_time":27.70877451},
{"learn":[0.4784786],"iteration":142,"passed_time":4.60702361,"remaining_time":27.60992471},
{"learn":[0.4760636871],"iteration":143,"passed_time":4.638005095,"remaining_time":27.57036362},
{"learn":[0.473522766],"iteration":144,"passed_time":4.661999965,"remaining_time":27.48972393},
{"learn":[0.4713984315],"iteration":145,"passed_time":4.69028987,"remaining_time":27.43498321},
{"learn":[0.4701357147],"iteration":146,"passed_time":4.71445395,"remaining_time":27.35666136},
{"learn":[0.4687704044],"iteration":147,"passed_time":4.737386788,"remaining_time":27.2719834},
{"learn":[0.4673356703],"iteration":148,"passed_time":4.765257519,"remaining_time":27.21633657},
{"learn":[0.4656398066],"iteration":149,"passed_time":4.791382104,"remaining_time":27.15116526},
{"learn":[0.4635632596],"iteration":150,"passed_time":4.822034688,"remaining_time":27.11196987},
{"learn":[0.4618238851],"iteration":151,"passed_time":4.852112498,"remaining_time":27.06968025},
{"learn":[0.4610204207],"iteration":152,"passed_time":4.877752296,"remaining_time":27.00298166},
{"learn":[0.4593286973],"iteration":153,"passed_time":4.89870734,"remaining_time":26.91108058},
{"learn":[0.4578814515],"iteration":154,"passed_time":4.927599944,"remaining_time":26.86336743},
{"learn":[0.4565596308],"iteration":155,"passed_time":4.960956276,"remaining_time":26.84004549},
{"learn":[0.4554006843],"iteration":156,"passed_time":4.997734211,"remaining_time":26.83496777},
{"learn":[0.4545654649],"iteration":157,"passed_time":5.022749231,"remaining_time":26.76680286},
{"learn":[0.4529242084],"iteration":158,"passed_time":5.0516267,"remaining_time":26.71961041},
{"learn":[0.451715996],"iteration":159,"passed_time":5.081405895,"remaining_time":26.67738095},
{"learn":[0.449851848],"iteration":160,"passed_time":5.107410322,"remaining_time":26.61563516},
{"learn":[0.4480703246],"iteration":161,"passed_time":5.141505318,"remaining_time":26.59618183},
{"learn":[0.4472512919],"iteration":162,"passed_time":5.16165857,"remaining_time":26.50495842},
{"learn":[0.4456877028],"iteration":163,"passed_time":5.188644893,"remaining_time":26.44943372},
{"learn":[0.4445253715],"iteration":164,"passed_time":5.218690202,"remaining_time":26.40973526},
{"learn":[0.443485052],"iteration":165,"passed_time":5.244727193,"remaining_time":26.35001493},
{"learn":[0.442115353],"iteration":166,"passed_time":5.274904554,"remaining_time":26.31135026},
{"learn":[0.4402749386],"iteration":167,"passed_time":5.299187924,"remaining_time":26.24359734},
{"learn":[0.4386010215],"iteration":168,"passed_time":5.322445143,"remaining_time":26.1713131},
{"learn":[0.4372870923],"iteration":169,"passed_time":5.348625193,"remaining_time":26.11387594},
{"learn":[0.4365780871],"iteration":170,"passed_time":5.370929199,"remaining_time":26.03801349},
{"learn":[0.4357474217],"iteration":171,"passed_time":5.392855329,"remaining_time":25.96095473},
{"learn":[,
{"learn":[0.4406821568],"iteration":172,"passed_time":5.427292057,"remaining_time":,
{"learn":[,
{"learn":[0.4397135149],"iteration":173,"passed_time":5.456197197,"remaining_time":,
{"learn":[,
{"learn":[0.4378044714],"iteration":174,"passed_time":5.483209119,"remaining_time",
{"learn":[0,
{"learn":[0.4366255283],"iteration":175,"passed_time":5.516397955,"remaining_time",
{"learn":[0,
{"learn":[0.4349238708],"iteration":176,"passed_time":5.541927548,"remaining_time,
{"learn":[0.,
{"learn":[0.433575043],"iteration":177,"passed_time":5.570637691,"remaining_ti,
{"learn":[0.42,
{"learn":[0.4320484319],"iteration":178,"passed_time":5.604829568,"remaining_ti,
{"learn":[0.42,
{"learn":[0.4304779684],"iteration":179,"passed_time":5.631457581,"remaining_ti,
{"learn":[0.42,
{"learn":[0.4288856174],"iteration":180,"passed_time":5.664342148,"remaining_time":25.63036585},
{"learn":[0.4274202813],"iteration":181,"passed_time":5.69683477,"remaining_time":25.60445517},
{"learn":[0.4260609184],"iteration":182,"passed_time":5.722290975,"remaining_time":25.54705862},
{"learn":[0.425063583],"iteration":183,"passed_time":5.746575025,"remaining_time":25.48481098},
{"learn":[0.4239394556],"iteration":184,"passed_time":5.772700228,"remaining_time":25.43108479},
{"learn":[0.4226797552],"iteration":185,"passed_time":5.798113992,"remaining_time":25.37454188},
{"learn":[0.4209193101],"iteration":186,"passed_time":5.82234699,"remaining_time":25.31319841},
{"learn":[0.4200356247],"iteration":187,"passed_time":5.852561075,"remaining_time":25.27808294},
{"learn":[0.4186244597],"iteration":188,"passed_time":5.875575731,"remaining_time":25.21212655},
{"learn":[0.4170340996],"iteration":189,"passed_time":5.905433695,"remaining_time":25.17579628},
{"learn":[0.4158857047],"iteration":190,"passed_time":5.932457839,"remaining_time":25.12753085},
{"learn":[0.4144627737],"iteration":191,"passed_time":5.960830445,"remaining_time":25.08516146},
{"learn":[0.4127157148],"iteration":192,"passed_time":5.997145681,"remaining_time":25.076148},
{"learn":[0.4120560145],"iteration":193,"passed_time":6.025670306,"remaining_time":25.03448591},
{"learn":[0.4108572664],"iteration":194,"passed_time":6.046554555,"remaining_time":24.96141752},
{"learn":[0.4097450443],"iteration":195,"passed_time":6.069071518,"remaining_time":24.89557908},
{"learn":[0.4086075919],"iteration":196,"passed_time":6.100197526,"remaining_time":24.86527215},
{"learn":[0.4075210226],"iteration":197,"passed_time":6.123388844,"remaining_time":24.80281744},
{"learn":[0.4061968164],"iteration":198,"passed_time":6.149296893,"remaining_time":24.75169252},
{"learn":[0.4040470428],"iteration":199,"passed_time":6.174686003,"remaining_time":24.69874401},
{"learn":[0.402213113],"iteration":200,"passed_time":6.203380458,"remaining_time":24.65920889},
{"learn":[0.4016392282],"iteration":201,"passed_time":6.226499443,"remaining_time":24.59775522},
{"learn":[0.4007069092],"iteration":202,"passed_time":6.252873781,"remaining_time":24.54946012},
{"learn":[0.3998082286],"iteration":203,"passed_time":6.276933816,"remaining_time":24.4923496},
{"learn":[0.3991880215],"iteration":204,"passed_time":6.30622093,"remaining_time":24.45583239},
{"learn":[0.3984361502],"iteration":205,"passed_time":6.334453659,"remaining_time":24.41532139},
{"learn":[0.3973539178],"iteration":206,"passed_time":6.362562351,"remaining_time":24.37445384},
{"learn":[0.3957661139],"iteration":207,"passed_time":6.387906029,"remaining_time":24.32318065},
{"learn":[0.3940781805],"iteration":208,"passed_time":6.411349105,"remaining_time":24.2649624},
{"learn":[0.392851784],"iteration":209,"passed_time":6.437292825,"remaining_time":24.21648253},
{"learn":[0.3922444703],"iteration":210,"passed_time":6.458078199,"remaining_time":24.14892748},
{"learn":[0.3910552559],"iteration":211,"passed_time":6.486217283,"remaining_time":24.10914726},
{"learn":[0.3897764149],"iteration":212,"passed_time":6.515270367,"remaining_time":24.07285342},
{"learn":[0.3883056615],"iteration":213,"passed_time":6.537907118,"remaining_time":24.01306072},
{"learn":[0.3876755866],"iteration":214,"passed_time":6.557289757,"remaining_time":23.94173237},
{"learn":[0.3869490413],"iteration":215,"passed_time":6.589075548,"remaining_time":23.91590384},
{"learn":[0.3858965273],"iteration":216,"passed_time":6.611059548,"remaining_time":23.85465266},
{"learn":[0.3846508835],"iteration":217,"passed_time":6.637124677,"remaining_time":23.80840136},
{"learn":[0.3824744682],"iteration":218,"passed_time":6.665823487,"remaining_time":23.77172668},
{"learn":[0.3814896517],"iteration":219,"passed_time":6.697900382,"remaining_time":23.74710136},
{"learn":[0.3808775592],"iteration":220,"passed_time":6.730298235,"remaining_time":23.72353993},
{"learn":[0.3795390811],"iteration":221,"passed_time":6.756180187,"remaining_time":23.6770639},
{"learn":[0.3779795279],"iteration":222,"passed_time":6.778995744,"remaining_time":23.62008831},
{"learn":[0.3771391144],"iteration":223,"passed_time":6.804376107,"remaining_time":23.57230294},
{"learn":[0.3762387776],"iteration":224,"passed_time":6.834438274,"remaining_time":23.54084294},
{"learn":[0.3746250038],"iteration":225,"passed_time":6.86452513,"remaining_time":23.50947987},
{"learn":[0.3737791239],"iteration":226,"passed_time":6.8863173,"remaining_time":23.44988226},
{"learn":[0.3722071487],"iteration":227,"passed_time":6.919180804,"remaining_time":23.42810342},
{"learn":[0.3708535057],"iteration":228,"passed_time":6.947268585,"remaining_time":23.39014882},
{"learn":[0.3702932244],"iteration":229,"passed_time":6.970563647,"remaining_time":23.33623482},
{"learn":[0.3688766758],"iteration":230,"passed_time":6.997330548,"remaining_time":23.29414368},
{"learn":[0.36812307],"iteration":231,"passed_time":7.025246218,"remaining_time":23.25598748},
{"learn":[0.3677429067],"iteration":232,"passed_time":7.049869692,"remaining_time":23.20708178},
{"learn":[0.3669545297],"iteration":233,"passed_time":7.076389285,"remaining_time":23.16459057},
{"learn":[0.3660512588],"iteration":234,"passed_time":7.104261923,"remaining_time":23.12663988},
{"learn":[0.3649338573],"iteration":235,"passed_time":7.13111122,"remaining_time":23.08546175},
{"learn":[0.3642613552],"iteration":236,"passed_time":7.156621784,"remaining_time":23.0400946},
{"learn":[0.3634155591],"iteration":237,"passed_time":7.181115084,"remaining_time":22.99163737},
{"learn":[0.3627508425],"iteration":238,"passed_time":7.208214014,"remaining_time":22.95167726},
{"learn":[0.3611644417],"iteration":239,"passed_time":7.234998757,"remaining_time":22.9108294},
{"learn":[0.3606299957],"iteration":240,"passed_time":7.263918606,"remaining_time":22.8768225},
{"learn":[0.3598404682],"iteration":241,"passed_time":7.286373494,"remaining_time":22.82260789},
{"learn":[0.3587263874],"iteration":242,"passed_time":7.311974924,"remaining_time":22.77845686},
{"learn":[0.357987303],"iteration":243,"passed_time":7.337249095,"remaining_time":22.73344392},
{"learn":[0.356762743],"iteration":244,"passed_time":7.368283276,"remaining_time":22.70634234},
{"learn":[0.3556112715],"iteration":245,"passed_time":7.397411956,"remaining_time":22.67336835},
{"learn":[0.3548477409],"iteration":246,"passed_time":7.425723101,"remaining_time":22.63793318},
{"learn":[0.3538614873],"iteration":247,"passed_time":7.452211754,"remaining_time":22.59702919},
{"learn":[0.3531041712],"iteration":248,"passed_time":7.475660213,"remaining_time":22.54707157},
{"learn":[0.3520641735],"iteration":249,"passed_time":7.502535934,"remaining_time":22.5076078},
{"learn":[0.3510312043],"iteration":250,"passed_time":7.529700614,"remaining_time":22.46910661},
{"learn":[0.3494377071],"iteration":251,"passed_time":7.55807854,"remaining_time":22.43429662},
{"learn":[0.3483823076],"iteration":252,"passed_time":7.58476299,"remaining_time":22.39453737},
{"learn":[0.3480287766],"iteration":253,"passed_time":7.607746785,"remaining_time":22.34401221},
{"learn":[0.3469060105],"iteration":254,"passed_time":7.635246776,"remaining_time":22.30689744},
{"learn":[0.34553461],"iteration":255,"passed_time":7.663211804,"remaining_time":22.27120931},
{"learn":[0.3445086233],"iteration":256,"passed_time":7.685978411,"remaining_time":22.22055237},
{"learn":[0.3430915978],"iteration":257,"passed_time":7.70938547,"remaining_time":22.17195356},
{"learn":[0.3422390083],"iteration":258,"passed_time":7.734889379,"remaining_time":22.12954838},
{"learn":[0.3416288952],"iteration":259,"passed_time":7.764755744,"remaining_time":22.09968943},
{"learn":[0.3408695355],"iteration":260,"passed_time":7.791601331,"remaining_time":22.06127733},
{"learn":[0.3394087681],"iteration":261,"passed_time":7.825622012,"remaining_time":22.04316429},
{"learn":[0.3380417464],"iteration":262,"passed_time":7.851641771,"remaining_time":22.00250945},
{"learn":[0.3371235126],"iteration":263,"passed_time":7.88070228,"remaining_time":21.97044272},
{"learn":[0.3360717707],"iteration":264,"passed_time":7.909649952,"remaining_time":21.93808572},
{"learn":[0.3353948212],"iteration":265,"passed_time":7.940148878,"remaining_time":21.91003487},
{"learn":[0.3344546494],"iteration":266,"passed_time":7.968038349,"remaining_time":21.87480191},
{"learn":[0.333615919],"iteration":267,"passed_time":7.993698706,"remaining_time":21.83353527},
{"learn":[0.3327451464],"iteration":268,"passed_time":8.021809965,"remaining_time":21.79904492},
{"learn":[0.3322260337],"iteration":269,"passed_time":8.051109395,"remaining_time":21.76781429},
{"learn":[0.3315026475],"iteration":270,"passed_time":8.075987908,"remaining_time":21.72470548},
{"learn":[0.3307183396],"iteration":271,"passed_time":8.104230519,"remaining_time":21.69073462},
{"learn":[0.3300805585],"iteration":272,"passed_time":8.132284758,"remaining_time":21.6563041},
{"learn":[0.3293596621],"iteration":273,"passed_time":8.156953548,"remaining_time":21.61294991},
{"learn":[0.3284950222],"iteration":274,"passed_time":8.189005792,"remaining_time":21.58919709},
{"learn":[0.3276078993],"iteration":275,"passed_time":8.212682855,"remaining_time":21.54341445},
{"learn":[0.3267254404],"iteration":276,"passed_time":8.239248173,"remaining_time":21.50533007},
{"learn":[0.3261061143],"iteration":277,"passed_time":8.269873511,"remaining_time":21.47787293},
{"learn":[0.3253692402],"iteration":278,"passed_time":8.297664214,"remaining_time":21.44306773},
{"learn":[0.3242698353],"iteration":279,"passed_time":8.331968037,"remaining_time":21.42506067},
{"learn":[0.323613252],"iteration":280,"passed_time":8.35958562,"remaining_time":21.3898294},
{"learn":[0.3231428923],"iteration":281,"passed_time":8.393685736,"remaining_time":21.3711573},
{"learn":[0.3222499458],"iteration":282,"passed_time":8.424989319,"remaining_time":21.34529096},
{"learn":[0.3212341362],"iteration":283,"passed_time":8.452243799,"remaining_time":21.30917803},
{"learn":[0.3204894505],"iteration":284,"passed_time":8.492571158,"remaining_time":21.30592413},
{"learn":[0.3196659776],"iteration":285,"passed_time":8.527488637,"remaining_time":21.2889052},
{"learn":[0.3192480136],"iteration":286,"passed_time":8.557032972,"remaining_time":21.25841292},
{"learn":[0.3180479027],"iteration":287,"passed_time":8.604343415,"remaining_time":21.271849},
{"learn":[0.316206625],"iteration":288,"passed_time":8.626652613,"remaining_time":21.22335643},
{"learn":[0.315133809],"iteration":289,"passed_time":8.655770415,"remaining_time":21.19171378},
{"learn":[0.3142781199],"iteration":290,"passed_time":8.684507696,"remaining_time":21.15916136},
{"learn":[0.3131262605],"iteration":291,"passed_time":8.713239897,"remaining_time":21.12662276},
{"learn":[0.3120038301],"iteration":292,"passed_time":8.737149321,"remaining_time":21.08247293},
{"learn":[0.310906361],"iteration":293,"passed_time":8.778471931,"remaining_time":21.08027613},
{"learn":[0.3099977396],"iteration":294,"passed_time":8.809762217,"remaining_time":21.05383852},
{"learn":[0.3091956772],"iteration":295,"passed_time":8.845216683,"remaining_time":21.03727211},
{"learn":[0.3084499875],"iteration":296,"passed_time":8.875165195,"remaining_time":21.0075459},
{"learn":[0.3073057887],"iteration":297,"passed_time":8.90521959,"remaining_time":20.97806762},
{"learn":[0.3067296418],"iteration":298,"passed_time":8.939679317,"remaining_time":20.95891372},
{"learn":[0.3058050555],"iteration":299,"passed_time":8.970636857,"remaining_time":20.931486},
{"learn":[0.3048566498],"iteration":300,"passed_time":8.993283963,"remaining_time":20.88473585},
{"learn":[0.3037877769],"iteration":301,"passed_time":9.018092954,"remaining_time":20.84314199},
{"learn":[0.3025572189],"iteration":302,"passed_time":9.04246053,"remaining_time":20.80064353},
{"learn":[0.3017963764],"iteration":303,"passed_time":9.065936656,"remaining_time":20.7562234},
{"learn":[0.3005550907],"iteration":304,"passed_time":9.088010768,"remaining_time":20.70874585},
{"learn":[0.2995398441],"iteration":305,"passed_time":9.11273915,"remaining_time":20.66745415},
{"learn":[0.2989677737],"iteration":306,"passed_time":9.137059012,"remaining_time":20.62534819},
{"learn":[0.2981525907],"iteration":307,"passed_time":9.164306346,"remaining_time":20.58993504},
{"learn":[0.2973958737],"iteration":308,"passed_time":9.192264314,"remaining_time":20.55616389},
{"learn":[0.2962648084],"iteration":309,"passed_time":9.216332762,"remaining_time":20.51377292},
{"learn":[0.2956637333],"iteration":310,"passed_time":9.239908541,"remaining_time":20.47040831},
{"learn":[0.2946619026],"iteration":311,"passed_time":9.266961513,"remaining_time":20.43483821},
{"learn":[0.293832467],"iteration":312,"passed_time":9.291035105,"remaining_time":20.39278312},
{"learn":[0.2934943711],"iteration":313,"passed_time":9.315950633,"remaining_time":20.35268196},
{"learn":[0.2926207116],"iteration":314,"passed_time":9.347579106,"remaining_time":20.3272752},
{"learn":[0.2916640574],"iteration":315,"passed_time":9.385030851,"remaining_time":20.31443387},
{"learn":[0.2914014415],"iteration":316,"passed_time":9.403413896,"remaining_time":20.26035234},
{"learn":[0.2907894741],"iteration":317,"passed_time":9.4422362,"remaining_time":20.25033047},
{"learn":[0.2901771188],"iteration":318,"passed_time":9.486107732,"remaining_time":20.2509071},
{"learn":[0.2896258499],"iteration":319,"passed_time":9.517974846,"remaining_time":20.22569655},
{"learn":[0.2889095806],"iteration":320,"passed_time":9.548973701,"remaining_time":20.19860792},
{"learn":[0.2882351143],"iteration":321,"passed_time":9.573879961,"remaining_time":20.1586665},
{"learn":[0.2871269566],"iteration":322,"passed_time":9.597143567,"remaining_time":20.11537522},
{"learn":[0.286464364],"iteration":323,"passed_time":9.623687214,"remaining_time":20.0790511},
{"learn":[0.286081286],"iteration":324,"passed_time":9.64705785,"remaining_time":20.03619707},
{"learn":[0.2853564983],"iteration":325,"passed_time":9.672224824,"remaining_time":19.99717648},
{"learn":[0.2845366928],"iteration":326,"passed_time":9.694571351,"remaining_time":19.95243584},
{"learn":[0.2835488269],"iteration":327,"passed_time":9.718230086,"remaining_time":19.91052018},
{"learn":[0.2828395465],"iteration":328,"passed_time":9.743322707,"remaining_time":19.87163993},
{"learn":[0.2823342537],"iteration":329,"passed_time":9.773383575,"remaining_time":19.84293029},
{"learn":[0.2815603419],"iteration":330,"passed_time":9.803013773,"remaining_time":19.81334204},
{"learn":[0.2807778881],"iteration":331,"passed_time":9.831120452,"remaining_time":19.78068814},
{"learn":[0.2803430651],"iteration":332,"passed_time":9.868045886,"remaining_time":19.76572554},
{"learn":[0.2795291751],"iteration":333,"passed_time":9.902620239,"remaining_time":19.74594335},
{"learn":[0.2788858228],"iteration":334,"passed_time":9.951861913,"remaining_time":19.75518857},
{"learn":[0.2779266102],"iteration":335,"passed_time":9.987284522,"remaining_time":19.73677655},
{"learn":[0.2772660389],"iteration":336,"passed_time":10.02128694,"remaining_time":19.71546955},
{"learn":[0.2765816266],"iteration":337,"passed_time":10.06171961,"remaining_time":19.70668161},
{"learn":[0.2756330696],"iteration":338,"passed_time":10.08536381,"remaining_time":19.66497191},
{"learn":[0.2748467423],"iteration":339,"passed_time":10.11007457,"remaining_time":19.62543887},
{"learn":[0.2739091338],"iteration":340,"passed_time":10.12899265,"remaining_time":19.5747981},
{"learn":[0.2733321942],"iteration":341,"passed_time":10.14972812,"remaining_,
{"learn":[0.2784,
{"learn":[0.2727306248],"iteration":342,"passed_time":10.1735961,"remaining_t,
{"learn":[0.2776487326],"iteration":343,"passed_time":10.20045441,"remaining_time":19.45202933},
{"learn":[0.2767648663],"iteration":344,"passed_time":10.24615307,"remaining_time":19.45284133},
{"learn":[0.2761367438],"iteration":345,"passed_time":10.29548803,"remaining_time":19.46025771},
{"learn":[0.275499892],"iteration":346,"passed_time":10.31701885,"remaining_time":19.41502394},
{"learn":[0.2751013299],"iteration":347,"passed_time":10.34750191,"remaining_time":19.38669898},
{"learn":[0.2742159889],"iteration":348,"passed_time":10.37368238,"remaining_time":19.3503359},
{"learn":[0.2732423639],"iteration":349,"passed_time":10.41238891,"remaining_time":19.33729368},
{"learn":[0.2725906175],"iteration":350,"passed_time":10.45052586,"remaining_time":19.32305209},
{"learn":[0.2721983357],"iteration":351,"passed_time":10.48350109,"remaining_time":19.29917245},
{"learn":[0.2714935628],"iteration":352,"passed_time":10.51698294,"remaining_time":19.27616986},
{"learn":[0.2704167585],"iteration":353,"passed_time":10.55106489,"remaining_time":19.25420316},
{"learn":[0.2699344698],"iteration":354,"passed_time":10.57907641,"remaining_time":19.22113884},
{"learn":[0.2693862758],"iteration":355,"passed_time":10.61958412,"remaining_time":19.21070835},
{"learn":[0.2687326819],"iteration":356,"passed_time":10.66718422,"remaining_time":19.21288363},
{"learn":[0.268099607],"iteration":357,"passed_time":10.6921023,"remaining_time":19.17410524},
{"learn":[0.2676473489],"iteration":358,"passed_time":10.72330294,"remaining_time":19.14662168},
{"learn":[0.2667468075],"iteration":359,"passed_time":10.75185358,"remaining_time":19.11440636},
{"learn":[0.265900652],"iteration":360,"passed_time":10.77710284,"remaining_time":19.07636763},
{"learn":[0.265163853],"iteration":361,"passed_time":10.80317095,"remaining_time":19.03984272},
{"learn":[0.2647455329],"iteration":362,"passed_time":10.83355501,"remaining_time":19.01094915},
{"learn":[0.2641053367],"iteration":363,"passed_time":10.86084414,"remaining_time":18.97663977},
{"learn":[0.2633965055],"iteration":364,"passed_time":10.88350208,"remaining_time":18.93431184},
{"learn":[0.262304522],"iteration":365,"passed_time":10.90805752,"remaining_time":18.89537832},
{"learn":[0.2616678047],"iteration":366,"passed_time":10.93689178,"remaining_time":18.86390326},
{"learn":[0.2609275674],"iteration":367,"passed_time":10.97091651,"remaining_time":18.84135662},
{"learn":[0.2602552036],"iteration":368,"passed_time":11.00501313,"remaining_time":18.81887069},
{"learn":[0.2598539152],"iteration":369,"passed_time":11.03318368,"remaining_time":18.78623167},
{"learn":[0.2590905842],"iteration":370,"passed_time":11.05512429,"remaining_time":18.74305439},
{"learn":[0.2584541468],"iteration":371,"passed_time":11.08064922,"remaining_time":18.70604224},
{"learn":[0.2579897955],"iteration":372,"passed_time":11.10992843,"remaining_time":18.67540248},
{"learn":[0.2576252043],"iteration":373,"passed_time":11.13786576,"remaining_time":18.64252397},
{"learn":[0.256711602],"iteration":374,"passed_time":11.16040257,"remaining_time":18.60067095},
{"learn":[0.2559962027],"iteration":375,"passed_time":11.18741892,"remaining_time":18.5663548},
{"learn":[0.2551461139],"iteration":376,"passed_time":11.20761949,"remaining_time":18.52081417},
{"learn":[0.2547120989],"iteration":377,"passed_time":11.24398486,"remaining_time":18.50200684},
{"learn":[0.2539236468],"iteration":378,"passed_time":11.27993929,"remaining_time":18.4824335},
{"learn":[0.2534840128],"iteration":379,"passed_time":11.32260864,"remaining_time":18.47372989},
{"learn":[0.2532177117],"iteration":380,"passed_time":11.35767218,"remaining_time":18.45249103},
{"learn":[0.2529578636],"iteration":381,"passed_time":11.39625556,"remaining_time":18.43687419},
{"learn":[0.2521289832],"iteration":382,"passed_time":11.43373058,"remaining_time":18.41935188},
{"learn":[0.2517062811],"iteration":383,"passed_time":11.46487063,"remaining_time":18.3915633},
{"learn":[0.2513689147],"iteration":384,"passed_time":11.49491349,"remaining_time":18.36200467},
{"learn":[0.2506564443],"iteration":385,"passed_time":11.51975341,"remaining_time":18.32416734},
{"learn":[0.2500504672],"iteration":386,"passed_time":11.54842872,"remaining_time":18.29247237},
{"learn":[0.2491528667],"iteration":387,"passed_time":11.57224845,"remaining_time":18.25313416},
{"learn":[0.248593915],"iteration":388,"passed_time":11.59535619,"remaining_time":18.2127574},
{"learn":[0.2483061937],"iteration":389,"passed_time":11.62434317,"remaining_time":18.18166496},
{"learn":[0.2478626814],"iteration":390,"passed_time":11.6560463,"remaining_time":18.15481381},
{"learn":[0.2471593057],"iteration":391,"passed_time":11.68685089,"remaining_time":18.12654424},
{"learn":[0.2465557308],"iteration":392,"passed_time":11.70616173,"remaining_time":18.08050934},
{"learn":[0.2459260134],"iteration":393,"passed_time":11.73373225,"remaining_time":18.04731407},
{"learn":[0.2453537916],"iteration":394,"passed_time":11.77367711,"remaining_time":18.03310039},
{"learn":[0.245027114],"iteration":395,"passed_time":11.81077639,"remaining_time":18.01441651},
{"learn":[0.2441748264],"iteration":396,"passed_time":11.86571117,"remaining_time":18.02273007},
{"learn":[0.2437706792],"iteration":397,"passed_time":11.90626525,"remaining_time":18.00897407},
{"learn":[0.243353547],"iteration":398,"passed_time":11.95229978,"remaining_time":18.00333876},
{"learn":[0.2428463041],"iteration":399,"passed_time":11.99063466,"remaining_time":17.98595199},
{"learn":[0.2422309032],"iteration":400,"passed_time":12.01166349,"remaining_time":17.94260955},
{"learn":[0.2419243812],"iteration":401,"passed_time":12.04741758,"remaining_time":17.92128286},
{"learn":[0.2410736747],"iteration":402,"passed_time":12.08263365,"remaining_time":17.89908757},
{"learn":[0.2402625926],"iteration":403,"passed_time":12.10811991,"remaining_time":17.86247392},
{"learn":[0.2394840577],"iteration":404,"passed_time":12.12811941,"remaining_time":17.81785444},
{"learn":[0.239015982],"iteration":405,"passed_time":12.15625524,"remaining_time":17.78526013},
{"learn":[0.2383916954],"iteration":406,"passed_time":12.18925035,"remaining_time":17.7597677},
{"learn":[0.2375150484],"iteration":407,"passed_time":12.21277981,"remaining_time":17.72050403},
{"learn":[0.2368062354],"iteration":408,"passed_time":12.25118876,"remaining_time":17.70281798},
{"learn":[0.2363361665],"iteration":409,"passed_time":12.27837869,"remaining_time":17.6688864},
{"learn":[0.235774141],"iteration":410,"passed_time":12.30345525,"remaining_time":17.63195898},
{"learn":[0.2351556328],"iteration":411,"passed_time":12.32781627,"remaining_time":17.59406788},
{"learn":[0.2348265961],"iteration":412,"passed_time":12.36025791,"remaining_time":17.56772735},
{"learn":[0.2338408644],"iteration":413,"passed_time":12.39247708,"remaining_time":17.54104244},
{"learn":[0.2332972901],"iteration":414,"passed_time":12.41888494,"remaining_time":17.50613901},
{"learn":[0.2328633761],"iteration":415,"passed_time":12.44915823,"remaining_time":17.4767029},
{"learn":[0.2323035055],"iteration":416,"passed_time":12.47549735,"remaining_time":17.44176248},
{"learn":[0.2320735223],"iteration":417,"passed_time":12.50827421,"remaining_time":17.41582677},
{"learn":[0.2314173611],"iteration":418,"passed_time":12.54420055,"remaining_time":17.39422558},
{"learn":[0.2309272346],"iteration":419,"passed_time":12.56992698,"remaining_time":17.35847059},
{"learn":[0.2305455565],"iteration":420,"passed_time":12.59852766,"remaining_time":17.32671619},
{"learn":[0.2301250663],"iteration":421,"passed_time":12.6389802,"remaining_time":17.31120985},
{"learn":[0.2296537474],"iteration":422,"passed_time":12.65781546,"remaining_time":17.26609815},
{"learn":[0.2291317502],"iteration":423,"passed_time":12.68468183,"remaining_time":17.2320206},
{"learn":[0.2285971394],"iteration":424,"passed_time":12.70984416,"remaining_time":17.19567151},
{"learn":[0.2275941515],"iteration":425,"passed_time":12.73843901,"remaining_time":17.16399998},
{"learn":[0.2270964287],"iteration":426,"passed_time":12.76298261,"remaining_time":17.12690641},
{"learn":[0.2265301799],"iteration":427,"passed_time":12.78430459,"remaining_time":17.08556595},
{"learn":[0.2260410956],"iteration":428,"passed_time":12.80866279,"remaining_time":17.04836004},
{"learn":[0.2256925221],"iteration":429,"passed_time":12.83481077,"remaining_time":17.01358637},
{"learn":[0.2251958694],"iteration":430,"passed_time":12.85540494,"remaining_time":16.97152067},
{"learn":[0.224804813],"iteration":431,"passed_time":12.87875432,"remaining_time":16.93317698},
{"learn":[0.2243806334],"iteration":432,"passed_time":12.90103466,"remaining_time":16.89350266},
{"learn":[0.2239685549],"iteration":433,"passed_time":12.92816448,"remaining_time":16.86023294},
{"learn":[0.2235135056],"iteration":434,"passed_time":12.95034727,"remaining_time":16.82056599},
{"learn":[0.2229153427],"iteration":435,"passed_time":12.97487768,"remaining_time":16.78401608},
{"learn":[0.2225975462],"iteration":436,"passed_time":12.99539179,"remaining_time":16.74234685},
{"learn":[0.2222677725],"iteration":43,
{"learn":[0.2253388553],"iteration":437,"passed_time":1,
{"learn":[0.2216742574],"iteration":,
{"learn":[0.22517351],"iteration":438,"passed_time":13.09135177,"remaining_time":16.72949508},
{"learn":[0.2248212954],"iteration":439,"passed_time":13.11517813,"remaining_time":16.69204489},
{"learn":[0.2241172841],"iteration":440,"passed_time":13.13947775,"remaining_time":16.65525637},
{"learn":[0.2238366712],"iteration":441,"passed_time":13.17028782,"remaining_time":16.62674345},
{"learn":[0.2228421345],"iteration":442,"passed_time":13.19306846,"remaining_time":16.58812445},
{"learn":[0.2226178963],"iteration":443,"passed_time":13.21700478,"remaining_time":16.55102401},
{"learn":[0.2222674067],"iteration":444,"passed_time":13.24635821,"remaining_time":16.52073889},
{"learn":[0.2215473157],"iteration":445,"passed_time":13.28860951,"remaining_time":16.50647908},
{"learn":[0.2212370372],"iteration":446,"passed_time":13.32483036,"remaining_time":16.48463354},
{"learn":[0.2207795012],"iteration":447,"passed_time":13.35701478,"remaining_time":16.45775035},
{"learn":[0.2204100196],"iteration":448,"passed_time":13.40000642,"remaining_time":16.44410587},
{"learn":[0.2199409053],"iteration":449,"passed_time":13.44578976,"remaining_time":16.43374304},
{"learn":[0.2195998176],"iteration":450,"passed_time":13.48054955,"remaining_time":16.40980422},
{"learn":[0.2192399232],"iteration":451,"passed_time":13.52890126,"remaining_time":16.40229622},
{"learn":[0.2187511159],"iteration":452,"passed_time":13.56721477,"remaining_time":16.38248671},
{"learn":[0.2180615297],"iteration":453,"passed_time":13.59519951,"remaining_time":16.35017386},
{"learn":[0.2178708091],"iteration":454,"passed_time":13.61719826,"remaining_time":16.31071001},
{"learn":[0.2174109002],"iteration":455,"passed_time":13.64798204,"remaining_time":16.28180314},
{"learn":[0.2168823636],"iteration":456,"passed_time":13.67908365,"remaining_time":16.25326569},
{"learn":[0.21639493],"iteration":457,"passed_time":13.70417191,"remaining_time":16.21760081},
{"learn":[0.2157323132],"iteration":458,"passed_time":13.73861465,"remaining_time":16.19300768},
{"learn":[0.2152125312],"iteration":459,"passed_time":13.7707165,"remaining_time":16.16562372},
{"learn":[0.2150386853],"iteration":460,"passed_time":13.80187517,"remaining_time":16.13711652},
{"learn":[0.2146124486],"iteration":461,"passed_time":13.83514527,"remaining_time":16.11105661},
{"learn":[0.2139274349],"iteration":462,"passed_time":13.8702321,"remaining_time":16.08707265},
{"learn":[0.2131740363],"iteration":463,"passed_time":13.89878044,"remaining_time":16.05548775},
{"learn":[0.213061712],"iteration":464,"passed_time":13.93402948,"remaining_time":16.03162531},
{"learn":[0.2124371507],"iteration":465,"passed_time":13.95859862,"remaining_time":15.99547567},
{"learn":[0.2121689752],"iteration":466,"passed_time":13.99725591,"remaining_time":15.97545482},
{"learn":[0.2119441713],"iteration":467,"passed_time":14.02096882,"remaining_time":15.93836626},
{"learn":[0.2117660567],"iteration":468,"passed_time":14.04932953,"remaining_time":15.90659697},
{"learn":[0.2114242632],"iteration":469,"passed_time":14.09817194,"remaining_time":15.89793857},
{"learn":[0.2109326319],"iteration":470,"passed_time":14.14250835,"remaining_time":15.88404865},
{"learn":[0.2105592068],"iteration":471,"passed_time":14.18757205,"remaining_time":15.87084331},
{"learn":[0.210182989],"iteration":472,"passed_time":14.2283366,"remaining_time":15.8527133},
{"learn":[0.2097544708],"iteration":473,"passed_time":14.25536972,"remaining_time":15.81924994},
{"learn":[0.2095065329],"iteration":474,"passed_time":14.29260706,"remaining_time":15.79709202},
{"learn":[0.2088987717],"iteration":475,"passed_time":14.32813785,"remaining_time":15.77299208},
{"learn":[0.2082651193],"iteration":476,"passed_time":14.36492586,"remaining_time":15.75022269},
{"learn":[0.2079316647],"iteration":477,"passed_time":14.39994752,"remaining_time":15.7254657},
{"learn":[0.2077155329],"iteration":478,"passed_time":14.43487836,"remaining_time":15.70056707},
{"learn":[0.2072629426],"iteration":479,"passed_time":14.4649534,"remaining_time":15.67036618},
{"learn":[0.2069151587],"iteration":480,"passed_time":14.49816054,"remaining_time":15.64354536},
{"learn":[0.2062737548],"iteration":481,"passed_time":14.52478284,"remaining_time":15.6096214},
{"learn":[0.2053624869],"iteration":482,"passed_time":14.55838438,"remaining_time":15.58319818},
{"learn":[0.2050860978],"iteration":483,"passed_time":14.59075246,"remaining_time":15.55543031},
{"learn":[0.2044158185],"iteration":484,"passed_time":14.61803373,"remaining_time":15.52224201},
{"learn":[0.2040292951],"iteration":485,"passed_time":14.64832268,"remaining_time":15.49225896},
{"learn":[0.2033287034],"iteration":486,"passed_time":14.68667316,"remaining_time":15.47076659},
{"learn":[0.2025998745],"iteration":487,"passed_time":14.7121249,"remaining_time":15.43567202},
{"learn":[0.2022595011],"iteration":488,"passed_time":14.74206596,"remaining_time":15.40530819},
{"learn":[0.2020355288],"iteration":489,"passed_time":14.76851839,"remaining_time":15.37131506},
{"learn":[0.2016044097],"iteration":490,"passed_time":14.79935583,"remaining_time":15.3418984},
{"learn":[0.2010990606],"iteration":491,"passed_time":14.83230467,"remaining_time":15.31465604},
{"learn":[0.2003992932],"iteration":492,"passed_time":14.85888588,"remaining_time":15.28084207},
{"learn":[0.1999561973],"iteration":493,"passed_time":14.880451,"remaining_time":15.24191944},
{"learn":[0.199546335],"iteration":494,"passed_time":14.90712695,"remaining_time":15.20828103},
{"learn":[0.1990676257],"iteration":495,"passed_time":14.9312573,"remaining_time":15.17208403},
{"learn":[0.1985272403],"iteration":496,"passed_time":14.96184809,"remaining_time":15.14247402},
{"learn":[0.1979182709],"iteration":497,"passed_time":14.99317999,"remaining_time":15.11360714},
{"learn":[0.1973475642],"iteration":498,"passed_time":15.02032996,"remaining_time":15.08053168},
{"learn":[0.1968533354],"iteration":499,"passed_time":15.05466958,"remaining_time":15.05466958},
{"learn":[0.1963936564],"iteration":500,"passed_time":15.08488556,"remaining_time":15.02466645},
{"learn":[0.1960299004],"iteration":501,"passed_time":15.11482832,"remaining_time":14.99439144},
{"learn":[0.1956834125],"iteration":502,"passed_time":15.14587349,"remaining_time":14.96520701},
{"learn":[0.1951439688],"iteration":503,"passed_time":15.17489714,"remaining_time":14.93402576},
{"learn":[0.1944913097],"iteration":504,"passed_time":15.19750556,"remaining_time":14.89656485},
{"learn":[0.1937908791],"iteration":505,"passed_time":15.22373108,"remaining_time":14.86269398},
{"learn":[0.1932438604],"iteration":506,"passed_time":15.25492033,"remaining_time":14.83367992},
{"learn":[0.1928230243],"iteration":507,"passed_time":15.28882077,"remaining_time":14.80728311},
{"learn":[0.1926260088],"iteration":508,"passed_time":15.31557204,"remaining_time":14.77396045},
{"learn":[0.1920955784],"iteration":509,"passed_time":15.34753277,"remaining_time":14.74566874},
{"learn":[0.1918585546],"iteration":510,"passed_time":15.37771279,"remaining_time":14.71565862},
{"learn":[0.1912565941],"iteration":511,"passed_time":15.40134055,"remaining_time":14.67940271},
{"learn":[0.1907676488],"iteration":512,"passed_time":15.42611798,"remaining_time":14.64428744},
{"learn":[0.1903351281],"iteration":513,"passed_time":15.44858401,"remaining_time":14.6070269},
{"learn":[0.190050993],"iteration":514,"passed_time":15.4755692,"remaining_time":14.57407973},
{"learn":[0.1897129076],"iteration":515,"passed_time":15.50192559,"remaining_time":14.54056586},
{"learn":[0.1895490813],"iteration":516,"passed_time":15.53015756,"remaining_time":14.50883192},
{"learn":[0.1891227775],"iteration":517,"passed_time":15.55946287,"remaining_time":14.47811024},
{"learn":[0.1887560542],"iteration":518,"passed_time":15.58855149,"remaining_time":14.44719319},
{"learn":[0.1883000682],"iteration":519,"passed_time":15.62184791,"remaining_time":14.4201673},
{"learn":[0.1877900179],"iteration":520,"passed_time":15.64474229,"remaining_time":14.38355385},
{"learn":[0.18748773],"iteration":521,"passed_time":15.66800443,"remaining_time":14.34732972},
{"learn":[0.1867655924],"iteration":522,"passed_time":15.69620423,"remaining_time":14.31565854},
{"learn":[0.1863546989],"iteration":523,"passed_time":15.71669738,"remaining_time":14.27699991},
{"learn":[0.1860773512],"iteration":524,"passed_time":15.74229323,"remaining_time":14.24302721},
{"learn":[0.1856802569],"iteration":525,"passed_time":15.76551949,"remaining_time":14.20695102},
{"learn":[0.1851939013],"iteration":526,"passed_time":15.79548023,"remaining_time":14.17696802},
{"learn":[0.1848246306],"iteration":527,"passed_time":15.82374456,"remaining_time":14.14546862},
{"learn":[0.1845499198],"iteration":528,"passed_time":15.84874142,"remaining_time":14.11107223},
{"learn":[0.1840438648],"iteration":529,"passed_time":15.87475517,"remaining_time":14.07761308},
{"learn":[0.1837758696],"iteration":530,"passed_time":15.90706384,"remaining_time":14.04974188},
{"learn":[0.1833597946],"iteration":531,"passed_time":15.9379354,"remaining_time":14.02058979},
{"learn":[0.1830393142],"iteration":532,"passed_time":15.96484231,"remaining_time":13.98795752},
{"learn":[0.1827379059],"iteration":533,"passed_time":15.98337677,"remaining_time":13.9480404},
{"learn":[0.1820347344],"iteration":534,"passed_time":16.01452653,"remaining_time":13.91916792},
{"learn":[0.1818048187],"iteration":535,"passed_time":16.04659009,"remaining_time":13.89107799},
{"learn":[0.1813599672],"iteration":536,"passed_time":16.07634126,"remaining_time":13.86097952},
{"learn":[0.1810904968],"iteration":537,"passed_time":16.10691278,"remaining_time":13.83158681},
{"learn":[0.1809204288],"iteration":538,"passed_time":16.13067232,"remaining_time":13.79636353},
{"learn":[0.1803278714],"iteration":539,"passed_time":16.15959516,"remaining_time":13.76558106},
{"learn":[0.1799669681],"iteration":540,"passed_time":16.18488699,"remaining_time":13.73172482},
{"learn":[0.1796146724],"iteration":541,"passed_time":16.20964469,"remaining_time":13.69744884},
{"learn":[0.1793677556],"iteration":542,"passed_time":16.24086575,"remaining_time":13.6686476},
{"learn":[0.1788710607],"iteration":543,"passed_time":16.26450843,"remaining_time":13.63348501},
{"learn":[0.17830914],"iteration":544,"passed_time":16.28798612,"remaining_time":13.59822695},
{"learn":[0.1779761393],"iteration":545,"passed_time":16.31875961,"remaining_time":13.56907851},
{"learn":[0.1775869926],"iteration":546,"passed_time":16.34408587,"remaining_time":13.53541298},
{"learn":[0.1772894571],"iteration":547,"passed_time":16.37076225,"remaining_time":13.50289149},
{"learn":[0.1770882705],"iteration":548,"passed_time":16.39202186,"remaining_time":13.46594146},
{"learn":[0.1767940172],"iteration":549,"passed_time":16.41422693,"remaining_time":13.42982203},
{"learn":[0.1763247296],"iteration":550,"passed_time":16.44208953,"remaining_time":13.39836334},
{"learn":[0.1758240752],"iteration":551,"passed_time":16.46828414,"remaining_time":13.36556394},
{"learn":[0.1756047398],"iteration":552,"passed_time":16.49380998,"remaining_time":13.33224785},
{"learn":[0.175172555],"iteration":553,"passed_time":16.53118495,"remaining_time":13.30849908},
{"learn":[0.1750131109],"iteration":554,"passed_time":16.55534259,"remaining_time":13.27410352},
{"learn":[0.1746453178],"iteration":555,"passed_time":16.58180996,"remaining_time":13.24158925},
{"learn":[0.1742438496],"iteration":556,"passed_time":16.60310408,"remaining_time":13.20498224},
{"learn":[0.1738306263],"iteration":557,"passed_time":16.62802482,"remaining_time":13.17130282},
{"learn":[0.1735886172],"iteration":558,"passed_time":16.65205554,"remaining_time":13.13695258},
{"learn":[0.1731816412],"iteration":559,"passed_time":16.68894953,"remaining_time":13.11274606},
{"learn":[0.1726797026],"iteration":560,"passed_time":16.71494602,"remaining_time":13.07996667},
{"learn":[0.1723694173],"iteration":561,"passed_time":16.73610611,"remaining_time":13.04344213},
{"learn":[0.1719608615],"iteration":562,"passed_time":16.75866867,"remaining_time":13.00806076},
{"learn":[0.1715350275],"iteration":563,"passed_time":16.78874341,"remaining_time":12.97853214},
{"learn":[0.1712284948],"iteration":564,"passed_time":16.81650284,"remaining_time":12.947219},
{"learn":[0.1708909502],"iteration":565,"passed_time":16.84558202,"remaining_time":12.91693038},
{"learn":[0.1706074274],"iteration":566,"passed_time":16.86791455,"remaining_time":12.88149382},
{"learn":[0.1701546063],"iteration":567,"passed_time":16.89468,"remaining_time":12.84947493},
{"learn":[0.1697120043],"iteration":568,"passed_time":16.91924226,"remaining_time":12.81580565},
{"learn":[0.1694290524],"iteration":569,"passed_time":16.94695246,"remaining_time":12.78454309},
{"learn":[0.1692504002],"iteration":570,"passed_time":16.97199543,"remaining_time":12.75128904},
{"learn":[0.1689096507],"iteration":571,"passed_time":17.00155794,"remaining_time":12.72144545},
{"learn":[0.1687331732],"iteration":572,"passed_time":17.0268313,"remaining_time":12.68840657},
{"learn":[0.1681600905],"iteration":573,"passed_time":17.04796754,"remaining_time":12.65232434},
{"learn":[0.1679485518],"iteration":574,"passed_time":17.0704865,"remaining_time":12.61731611},
{"learn":[0.1677214689],"iteration":575,"passed_time":17.09500498,"remaining_time":12.58382311},
{"learn":[0.1674321959],"iteration":576,"passed_time":17.12854976,"remaining_time":12.55697842},
{"learn":[0.1671831983],"iteration":577,"passed_time":17.15109236,"remaining_time":12.52207781},
{"learn":[0.1670747321],"iteration":578,"passed_time":17.18225833,"remaining_time":12.49349008},
{"learn":[0.1667040413],"iteration":579,"passed_time":17.21431853,"remaining_time":12.46554101},
{"learn":[0.1663752019],"iteration":580,"passed_time":17.24323376,"remaining_time":12.43530972},
{"learn":[0.1660965774],"iteration":581,"passed_time":17.26272643,"remaining_time":12.39831555},
{"learn":[0.1656888855],"iteration":582,"passed_time":17.2858046,"remaining_time":12.363946},
{"learn":[0.1656095118],"iteration":583,"passed_time":17.31605018,"remaining_time":12.33472068},
{"learn":[0.1651334637],"iteration":584,"passed_time":17.34363186,"remaining_time":12.30360209},
{"learn":[0.1649487618],"iteration":585,"passed_time":17.37266265,"remaining_time":12.27351934},
{"learn":[0.1647100173],"iteration":586,"passed_time":17.39562891,"remaining_time":12.23917332},
{"learn":[0.1644722543],"iteration":587,"passed_time":17.41915669,"remaining_time":12.20525945},
{"learn":[0.1642858833],"iteration":588,"passed_time":17.44247744,"remaining_time":12.17123638},
{"learn":[0.1637576783],"iteration":589,"passed_time":17.47199052,"remaining_time":12.14155273},
{"learn":[0.1635617504],"iteration":590,"passed_time":17.4985203,"remaining_time":12.10980508},
{"learn":[0.1632327194],"iteration":591,"passed_time":17.52540857,"remaining_time":12.07832212},
{"learn":[0.1628609022],"iteration":592,"passed_time":17.54989256,"remaining_time":12.04520451},
{"learn":[0.1626719535],"iteration":593,"passed_time":17.56922727,"remaining_time":12.00859642},
{"learn":[0.1624346317],"iteration":594,"passed_time":17.59437118,"remaining_time":11.97600055},
{"learn":[0.1620954057],"iteration":595,"passed_time":17.61496307,"remaining_time":11.94034409},
{"learn":[0.1616089293],"iteration":596,"passed_time":17.64396297,"remaining_time":11.91041387},
{"learn":[0.1612620439],"iteration":597,"passed_time":17.67736721,"remaining_time":11.88344752},
{"learn":[0.1606101277],"iteration":598,"passed_time":17.70744079,"remaining_time":11.85422998},
{"learn":[0.1603808362],"iteration":599,"passed_time":17.73171646,"remaining_time":11.82114431},
{"learn":[0.1599993893],"iteration":600,"passed_time":17.75597147,"remaining_time":11.78807424},
{"learn":[0.1596344597],"iteration":601,"passed_time":17.78304946,"remaining_time":11.75689981},
{"learn":[0.1593451633],"iteration":602,"passed_time":17.80609048,"remaining_time":11.72308113},
{"learn":[0.158798901],"iteration":603,"passed_time":17.8332999,"remaining_time":11.69203106},
{"learn":[0.1585350322],"iteration":604,"passed_time":17.8630831,"remaining_time":11.66267409},
{"learn":[0.1583043105],"iteration":605,"passed_time":17.88899638,"remaining_time":11.63079963},
{"learn":[0.1580961873],"iteration":606,"passed_time":17.91226985,"remaining_time":11.59723567},
{"learn":[0.1577611387],"iteration":607,"passed_time":17.93957638,"remaining_time":11.56630582},
{"learn":[0.1574030956],"iteration":608,"passed_time":17.96417822,"remaining_time":11.53365137},
{"learn":[0.1572429254],"iteration":609,"passed_time":17.98962709,"remaining_time":11.50156486},
{"learn":[0.1568697925],"iteration":610,"passed_time":18.0145141,"remaining_time":11.46914237},
{"learn":[0.1564713976],"iteration":611,"passed_time":18.03826568,"remaining_time":11.43602465},
{"learn":[0.1560663164],"iteration":612,"passed_time":18.06488768,"remaining_time":11.40474964},
{"learn":[0.1556482238],"iteration":613,"passed_time":18.09304708,"remaining_time":11.37445631},
{"learn":[0.1552923116],"iteration":614,"passed_time":18.12164539,"remaining_time":11.34444468},
{"learn":[0.1550328969],"iteration":615,"passed_time":18.13925102,"remaining_time":11.30758505},
{"learn":[0.1548058888],"iteration":616,"passed_time":18.16601634,"remaining_time":11.27647368},
{"learn":[0.1544634663],"iteration":617,"passed_time":18.19450552,"remaining_time":11.24644193},
{"learn":[0.1542932516],"iteration":618,"passed_time":18.22207914,"remaining_time":11.21585162},
{"learn":[0.1541653177],"iteration":619,"passed_time":18.25200399,"remaining_time":11.18671212},
{"learn":[0.1538680496],"iteration":620,"passed_time":18.27348819,"remaining_time":11.15241872},
{"learn":[0.1535700463],"iteration":621,"passed_time":18.29630302,"remaining_time":11.11897515},
{"learn":[0.1533115995],"iteration":622,"passed_time":18.32245232,"remaining_time":11.0875835},
{"learn":[0.1530361186],"iteration":623,"passed_time":18.34903468,"remaining_time":11.05646962},
{"learn":[0.1526556208],"iteration":624,"passed_time":18.37592709,"remaining_time":11.02555625},
{"learn":[0.1523341556],"iteration":625,"passed_time":18.40648876,"remaining_time":10.99684791},
{"learn":[0.1521544042],"iteration":626,"passed_time":18.43771175,"remaining_time":10.96852709},
{"learn":[0.151854892],"iteration":627,"passed_time":18.46851037,"remaining_time":10.93994563},
{"learn":[0.1515397633],"iteration":628,"passed_time":18.50047636,"remaining_time":10.91204568},
{"learn":[0.1514405128],"iteration":629,"passed_time":18.5365321,"remaining_time":10.88653473},
{"learn":[0.151259513],"iteration":630,"passed_time":18.55547837,"remaining_time":10.85098498},
{"learn":[0.1507960293],"iteration":631,"passed_time":18.57996849,"remaining_time":10.81871583},
{"learn":[0.1504704261],"iteration":632,"passed_time":18.6157596,"remaining_time":10.79302334},
{"learn":[0.1502050184],"iteration":633,"passed_time":18.64180859,"remaining_time":10.76167499},
{"learn":[0.1499290649],"iteration":634,"passed_time":18.66340248,"remaining_time":10.72778253},
{"learn":[0.1496601216],"iteration":635,"passed_time":18.69724962,"remaining_time":10.70094161},
{"learn":[0.1494396964],"iteration":636,"passed_time":18.7229433,"remaining_time":10.66943237},
{"learn":[0.1491576429],"iteration":637,"passed_time":18.75290458,"remaining_time":10.64036279},
{"learn":[0.1488773618],"iteration":638,"passed_time":18.78025642,"remaining_time":10.60981623},
{"learn":[0.1486021809],"iteration":639,"passed_time":18.80310853,"remaining_time":10.57674855},
{"learn":[0.1484225047],"iteration":640,"passed_time":18.83367677,"remaining_time":10.54803426},
{"learn":[0.1481157056],"iteration":641,"passed_time":18.85484764,"remaining_time":10.51407392},
{"learn":[0.1478156015],"iteration":642,"passed_time":18.88227061,"remaining_time":10.48362459},
{"learn":[0.1474867092],"iteration":643,"passed_time":18.90490874,"remaining_time":10.45053962},
{"learn":[0.147287484],"iteration":644,"passed_time":18.92687495,"remaining_time":10.41711722},
{"learn":[0.1469970566],"iteration":645,"passed_time":18.9461372,"remaining_time":10.38224856},
{"learn":[0.1466014135],"iteration":646,"passed_time":18.98069118,"remaining_time":10.35577123},
{"learn":[0.1464200991],"iteration":647,"passed_time":19.00517213,"remaining_time":10.32379721},
{"learn":[0.1459195341],"iteration":648,"passed_time":19.02742155,"remaining_time":10.29063939},
{"learn":[0.1456227713],"iteration":649,"passed_time":19.05412977,"remaining_time":10.25991603},
{"learn":[0.1452993482],"iteration":650,"passed_time":19.08348445,"remaining_time":10.23062377},
{"learn":[0.1449788711],"iteration":651,"passed_time":19.10844249,"remaining_time":10.19898464},
{"learn":[0.1448609747],"iteration":652,"passed_time":19.13195308,"remaining_time":10.16659681},
{"learn":[0.1446545758],"iteration":653,"passed_time":19.16144101,"remaining_time":10.13739846},
{"learn":[0.1443086752],"iteration":654,"passed_time":19.18997219,"remaining_time":10.10769528},
{"learn":[0.1441518777],"iteration":655,"passed_time":19.21536811,"remaining_time":10.07635157},
{"learn":[0.14384584],"iteration":656,"passed_time":19.23390643,"remaining_time":10.04144582},
{"learn":[0.1436485909],"iteration":657,"passed_time":19.26837868,"remaining_time":10.01487159},
{"learn":[0.1433371998],"iteration":658,"passed_time":19.29852254,"remaining_time":9.986033665},
{"learn":[0.1430847059],"iteration":659,"passed_time":19.32360761,"remaining_time":9.954585741},
{"learn":[0.1429260773],"iteration":660,"passed_time":19.35396893,"remaining_time":9.925863036},
{"learn":[0.1426013921],"iteration":661,"passed_time":19.38268316,"remaining_time":9.896294424},
{"learn":[0.1423921287],"iteration":662,"passed_time":19.4094542,"remaining_time":9.865740671},
{"learn":[0.1422577502],"iteration":663,"passed_time":19.43412211,"remaining_time":9.83413408},
{"learn":[0.1419332822],"iteration":664,"passed_time":19.45987084,"remaining_time":9.803092829},
{"learn":[0.1416738845],"iteration":665,"passed_time":19.48239779,"remaining_time":9.770451743},
{"learn":[0.1413193881],"iteration":666,"passed_time":19.50932789,"remaining_time":9.740039262},
{"learn":[0.1411212709],"iteration":667,"passed_time":19.54127775,"remaining_time":9.712132054},
{"learn":[0.14101284],"iteration":668,"passed_time":19.56341333,"remaining_time":9.679356967},
{"learn":[0.1405394024],"iteration":669,"passed_time":19.58900096,"remaining_time":9.648313905},
{"learn":[0.1403864237],"iteration":670,"passed_time":19.61603277,"remaining_time":9.617995203},
{"learn":[0.1402288981],"iteration":671,"passed_time":19.64438537,"remaining_time":9.588330954},
{"learn":[0.1400639501],"iteration":672,"passed_time":19.67267456,"remaining_time":9.558639791},
{"learn":[0.1398927014],"iteration":673,"passed_time":19.70148698,"remaining_time":9.529205871},
{"learn":[0.1397062049],"iteration":674,"passed_time":19.73010965,"remaining_time":9.499682422},
{"learn":[0.1395529189],"iteration":675,"passed_time":19.75449291,"remaining_time":9.468129738},
{"learn":[0.1392916377],"iteration":676,"passed_time":19.77547771,"remaining_time":9.434976808},
{"learn":[0.1389746394],"iteration":677,"passed_time":19.80165227,"remaining_time":9.404324531},
{"learn":[0.1387153545],"iteration":678,"passed_time":19.82842322,"remaining_time":9.373967382},
{"learn":[0.1382852321],"iteration":679,"passed_time":19.85373784,"remaining_time":9.342935454},
{"learn":[0.1379932928],"iteration":680,"passed_time":19.87915725,"remaining_time":9.311969403},
{"learn":[0.1377832138],"iteration":681,"passed_time":19.90184694,"remaining_time":9.279746814},
{"learn":[0.1373840123],"iteration":682,"passed_time":19.93330711,"remaining_time":9.251622771},
{"learn":[0.136960449],"iteration":683,"passed_time":19.95926705,"remaining_time":9.220947935},
{"learn":[0.1365688442],"iteration":684,"passed_time":19.98966853,"remaining_time":9.192329323},
{"learn":[0.1362919408],"iteration":685,"passed_time":20.01721391,"remaining_time":9.162398205},
{"learn":[0.1361490105],"iteration":686,"passed_time":20.04180682,"remaining_time":9.13112887},
{"learn":[0.1360494971],"iteration":687,"passed_time":20.06717418,"remaining_time":9.100230153},
{"learn":[0.1359311211],"iteration":688,"passed_time":20.09712431,"remaining_time":9.071416053},
{"learn":[0.1357393067],"iteration":689,"passed_time":20.11907576,"remaining_time":9.039005051},
{"learn":[0.1356030127],"iteration":690,"passed_time":20.13864562,"remaining_time":9.005559331},
{"learn":[0.1354005557],"iteration":691,"passed_time":20.16219392,"remaining_time":8.973924462},
{"learn":[0.135144896],"iteration":692,"passed_time":20.18430544,"remaining_time":8.941676436},
{"learn":[0.1350852895],"iteration":693,"passed_time":20.20970475,"remaining_time":8.910907281},
{"learn":[0.1349456846],"iteration":694,"passed_time":20.23469141,"remaining_time":8.879972489},
{"learn":[0.1347477823],"iteration":695,"passed_time":20.26877514,"remaining_time":8.853028223},
{"learn":[0.1345543267],"iteration":696,"passed_time":20.29435812,"remaining_time":8.82236802},
{"learn":[0.1343612268],"iteration":697,"passed_time":20.32505487,"remaining_time":8.793934913},
{"learn":[0.1341793215],"iteration":698,"passed_time":20.34810845,"remaining_time":8.76220407},
{"learn":[0.1339078051],"iteration":699,"passed_time":20.38122823,"remaining_time":8.734812098},
{"learn":[0.1336779624],"iteration":700,"passed_time":20.40652937,"remaining_time":8.704068875},
{"learn":[0.1333290288],"iteration":701,"passed_time":20.42833425,"remaining_time":8.671856991},
{"learn":[0.1331312054],"iteration":702,"passed_time":20.45515169,"remaining_time":8.641792393},
{"learn":[0.1329951674],"iteration":703,"passed_time":20.48316942,"remaining_time":8.612241687},
{"learn":[0.1328244846],"iteration":704,"passed_time":20.51333209,"remaining_time":8.58359286},
{"learn":[0.1325008081],"iteration":705,"passed_time":20.5476801,"remaining_time":8.556682649},
{"learn":[0.1321580593],"iteration":706,"passed_time":20.57319569,"remaining_time":8.526091001},
{"learn":[0.1320201808],"iteration":707,"passed_time":20.59119602,"remaining_time":8.492414177},
{"learn":[0.13177663],"iteration":708,"passed_time":20.61406407,"remaining_time":8.460779468},
{"learn":[0.1316293028],"iteration":709,"passed_time":20.63718931,"remaining_time":8.429274505},
{"learn":[0.1314124111],"iteration":710,"passed_time":20.65795879,"remaining_time":8.39683557},
{"learn":[0.131093897],"iteration":711,"passed_time":20.67963646,"remaining_time":8.364796772},
{"learn":[0.1307507539],"iteration":712,"passed_time":20.7041621,"remaining_time":8.333933411},
{"learn":[0.1305212625],"iteration":713,"passed_time":20.72367815,"remaining_time":8.301081163},
{"learn":[0.1303094741],"iteration":714,"passed_time":20.74930265,"remaining_time":8.270701057},
{"learn":[0.1300599012],"iteration":715,"passed_time":20.77391314,"remaining_time":8.23993203},
{"learn":[0.1297137142],"iteration":716,"passed_time":20.79661384,"remaining_time":8.208426382},
{"learn":[0.1294601391],"iteration":717,"passed_time":20.82061088,"remaining_time":8.177454414},
{"learn":[0.1292801069],"iteration":718,"passed_time":20.84717369,"remaining_time":8.147504599},
{"learn":[0.128885546],"iteration":719,"passed_time":20.87954702,"remaining_time":8.119823841},
{"learn":[0.1288027297],"iteration":720,"passed_time":20.90901742,"remaining_time":8.09100674},
{"learn":[0.1286496687],"iteration":721,"passed_time":20.93496378,"remaining_time":8.060830931},
{"learn":[0.128395502],"iteration":722,"passed_time":20.95843898,"remaining_time":8.029720052},
{"learn":[0.1279938745],"iteration":723,"passed_time":20.97690339,"remaining_time":7.996720077},
{"learn":[0.1277431882],"iteration":724,"passed_time":20.99517289,"remaining_time":7.963686268},
{"learn":[0.1275192653],"iteration":725,"passed_time":21.01652315,"remaining_time":7.931855845},
{"learn":[0.1272258871],"iteration":726,"passed_time":21.03587116,"remaining_time":7.899302375},
{"learn":[0.1271317368],"iteration":727,"passed_time":21.05555071,"remaining_time":7.866909057},
{"learn":[0.1268392467],"iteration":728,"passed_time":21.08026563,"remaining_time":7.836422479},
{"learn":[0.1266536723],"iteration":729,"passed_time":21.10512403,"remaining_time":7.806004778},
{"learn":[0.1264344076],"iteration":730,"passed_time":21.12696289,"remaining_time":7.77449113},
{"learn":[0.1262534965],"iteration":731,"passed_time":21.15078926,"remaining_time":7.743731588},
{"learn":[0.1261356738],"iteration":732,"passed_time":21.17309897,"remaining_time":7.712438507},
{"learn":[0.1259175336],"iteration":733,"passed_time":21.1990391,"remaining_time":7.682485558},
{"learn":[0.1257142942],"iteration":734,"passed_time":21.22099765,"remaining_time":7.651107997},
{"learn":[0.125518058],"iteration":735,"passed_time":21.24119219,"remaining_time":7.619123286},
{"learn":[0.1252351847],"iteration":736,"passed_time":21.26124912,"remaining_time":7.587121463},
{"learn":[0.1250248296],"iteration":737,"passed_time":21.28803005,"remaining_time":7.557539122},
{"learn":[0.1246498198],"iteration":738,"passed_time":21.31412451,"remaining_time":7.527721916},
{"learn":[0.1244563037],"iteration":7,
{"learn":[0.1184901323],"iteration":740,"passed_time":21,
{"learn":[0.1242412823],"iteration":7,
{"learn":[0.1182131893],"iteration":741,"passed_time":21,
{"learn":[0.1239732451],"iteration":7,
{"learn":[0.1179954497],"iteration":742,"passed_time":21,
{"learn":[0.1237898503],"iteration":,
{"learn":[0.1177670193],"iteration":743,"passed_time":21.40290321,"remaining_time":7.364439816},
{"learn":[0.1174817131],"iteration":744,"passed_time":21.43223805,"remaining_time":7.335866714},
{"learn":[0.1172980796],"iteration":745,"passed_time":21.45457918,"remaining_time":7.304910337},
{"learn":[0.1171143862],"iteration":746,"passed_time":21.47886668,"remaining_time":7.274636237},
{"learn":[0.1169240982],"iteration":747,"passed_time":21.51151721,"remaining_time":7.247195636},
{"learn":[0.1167866155],"iteration":748,"passed_time":21.5418097,"remaining_time":7.218950916},
{"learn":[0.1164199687],"iteration":749,"passed_time":21.58159643,"remaining_time":7.193865477},
{"learn":[0.1160855963],"iteration":750,"passed_time":21.61669574,"remaining_time":7.167186736},
{"learn":[0.1158844196],"iteration":751,"passed_time":21.6527045,"remaining_time":7.140785525},
{"learn":[0.1156642766],"iteration":752,"passed_time":21.69817077,"remaining_time":7.117461064},
{"learn":[0.1154449678],"iteration":753,"passed_time":21.73383426,"remaining_time":7.090879611},
{"learn":[0.1152853154],"iteration":754,"passed_time":21.76582603,"remaining_time":7.063082621},
{"learn":[0.115140619],"iteration":755,"passed_time":21.79408152,"remaining_time":7.034068638},
{"learn":[0.1149651282],"iteration":756,"passed_time":21.82342289,"remaining_time":7.005405235},
{"learn":[0.1147592526],"iteration":757,"passed_time":21.85683611,"remaining_time":6.978040024},
{"learn":[0.114492123],"iteration":758,"passed_time":21.88618626,"remaining_time":6.94936876},
{"learn":[0.1142704386],"iteration":759,"passed_time":21.91667236,"remaining_time":6.921054428},
{"learn":[0.1141224285],"iteration":760,"passed_time":21.94824486,"remaining_time":6.893075587},
{"learn":[0.1138678967],"iteration":761,"passed_time":21.97687727,"remaining_time":6.864169015},
{"learn":[0.1137064293],"iteration":762,"passed_time":22.007983,"remaining_time":6.836031416},
{"learn":[0.1136047716],"iteration":763,"passed_time":22.04058432,"remaining_time":6.808348035},
{"learn":[0.1133720049],"iteration":764,"passed_time":22.06532381,"remaining_time":6.778236725},
{"learn":[0.1131646538],"iteration":765,"passed_time":22.10133396,"remaining_time":6.751582438},
{"learn":[0.1129564863],"iteration":766,"passed_time":22.13286649,"remaining_time":6.723543537},
{"learn":[0.1127831681],"iteration":767,"passed_time":22.1553061,"remaining_time":6.692748716},
{"learn":[0.1125782509],"iteration":768,"passed_time":22.17571315,"remaining_time":6.661365067},
{"learn":[0.1123515324],"iteration":769,"passed_time":22.20454566,"remaining_time":6.632526625},
{"learn":[0.1122092324],"iteration":770,"passed_time":22.23233804,"remaining_time":6.603379263},
{"learn":[0.1120481343],"iteration":771,"passed_time":22.26251327,"remaining_time":6.574939153},
{"learn":[0.111765659],"iteration":772,"passed_time":22.28854298,"remaining_time":6.545277174},
{"learn":[0.1116608935],"iteration":773,"passed_time":22.32064142,"remaining_time":6.517396589},
{"learn":[0.1115132361],"iteration":774,"passed_time":22.34859232,"remaining_time":6.488300996},
{"learn":[0.1113932232],"iteration":775,"passed_time":22.36838053,"remaining_time":6.456852112},
{"learn":[0.1112338148],"iteration":776,"passed_time":22.38987375,"remaining_time":6.425922583},
{"learn":[0.1109126089],"iteration":777,"passed_time":22.42591056,"remaining_time":6.399167281},
{"learn":[0.1107784456],"iteration":778,"passed_time":22.45128891,"remaining_time":6.369364377},
{"learn":[0.110676591],"iteration":779,"passed_time":22.47487417,"remaining_time":6.339067072},
{"learn":[0.110569711],"iteration":780,"passed_time":22.50058206,"remaining_time":6.309382164},
{"learn":[0.1104004915],"iteration":781,"passed_time":22.52303432,"remaining_time":6.278799848},
{"learn":[0.1101611792],"iteration":782,"passed_time":22.55259402,"remaining_time":6.250208048},
{"learn":[0.1100067926],"iteration":783,"passed_time":22.57968332,"remaining_time":6.22093316},
{"learn":[0.1097324458],"iteration":784,"passed_time":22.61559295,"remaining_time":6.194079598},
{"learn":[0.1094863449],"iteration":785,"passed_time":22.65235245,"remaining_time":6.167434383},
{"learn":[0.1092890857],"iteration":786,"passed_time":22.68995672,"remaining_time":6.140992099},
{"learn":[0.1091167971],"iteration":787,"passed_time":22.73427661,"remaining_time":6.116328226},
{"learn":[0.1090144989],"iteration":788,"passed_time":22.7688298,"remaining_time":6.089002646},
{"learn":[0.1088053505],"iteration":789,"passed_time":22.79718626,"remaining_time":6.060011538},
{"learn":[0.1086590711],"iteration":790,"passed_time":22.82465654,"remaining_time":6.030787886},
{"learn":[0.1085135198],"iteration":791,"passed_time":22.850832,"remaining_time":6.001228607},
{"learn":[0.1082810689],"iteration":792,"passed_time":22.88002081,"remaining_time":5.972464447},
{"learn":[0.1081384036],"iteration":793,"passed_time":22.91457613,"remaining_time":5.945091541},
{"learn":[0.1080237604],"iteration":794,"passed_time":22.94055992,"remaining_time":5.915490295},
{"learn":[0.107789079],"iteration":795,"passed_time":22.96534269,"remaining_time":5.885590338},
{"learn":[0.10769042],"iteration":796,"passed_time":22.99013202,"remaining_time":5.855704893},
{"learn":[0.1075794698],"iteration":797,"passed_time":23.01892891,"remaining_time":5.826846666},
{"learn":[0.1073946321],"iteration":798,"passed_time":23.05027932,"remaining_time":5.798630967},
{"learn":[0.1071539062],"iteration":799,"passed_time":23.08380302,"remaining_time":5.770950756},
{"learn":[0.1069644932],"iteration":800,"passed_time":23.10333574,"remaining_time":5.739780039},
{"learn":[0.1068043165],"iteration":801,"passed_time":23.12900945,"remaining_time":5.710154453},
{"learn":[0.106560607],"iteration":802,"passed_time":23.15312105,"remaining_time":5.680155476},
{"learn":[0.1062756385],"iteration":803,"passed_time":23.18000378,"remaining_time":5.650846694},
{"learn":[0.1059831453],"iteration":804,"passed_time":23.20409288,"remaining_time":5.620867219},
{"learn":[0.1057927298],"iteration":805,"passed_time":23.23134649,"remaining_time":5.591664044},
{"learn":[0.1056346722],"iteration":806,"passed_time":23.26287061,"remaining_time":5.563487024},
{"learn":[0.1055388931],"iteration":807,"passed_time":23.29843463,"remaining_time":5.536261694},
{"learn":[0.105367137],"iteration":808,"passed_time":23.32342849,"remaining_time":5.506520199},
{"learn":[0.1051813627],"iteration":809,"passed_time":23.34686582,"remaining_time":5.476425316},
{"learn":[0.1049983207],"iteration":810,"passed_time":23.37346564,"remaining_time":5.447083853},
{"learn":[0.10478527],"iteration":811,"passed_time":23.39842825,"remaining_time":5.417370087},
{"learn":[0.1045066963],"iteration":812,"passed_time":23.42249293,"remaining_time":5.387461473},
{"learn":[0.1043908346],"iteration":813,"passed_time":23.44924779,"remaining_time":5.358181928},
{"learn":[0.1042015769],"iteration":814,"passed_time":23.47682084,"remaining_time":5.329094301},
{"learn":[0.1041228971],"iteration":815,"passed_time":23.50895964,"remaining_time":5.301039918},
{"learn":[0.1038621166],"iteration":816,"passed_time":23.53717776,"remaining_time":5.272097344},
{"learn":[0.1036586557],"iteration":817,"passed_time":23.5626618,"remaining_time":5.242548224},
{"learn":[0.1034918917],"iteration":818,"passed_time":23.58571227,"remaining_time":5.21247121},
{"learn":[0.1033714145],"iteration":819,"passed_time":23.60956845,"remaining_time":5.182588196},
{"learn":[0.1032503201],"iteration":820,"passed_time":23.64130612,"remaining_time":5.154438241},
{"learn":[0.1030178867],"iteration":821,"passed_time":23.66591619,"remaining_time":5.12473611},
{"learn":[0.1028972534],"iteration":822,"passed_time":23.69105482,"remaining_time":5.095160028},
{"learn":[0.1027490241],"iteration":823,"passed_time":23.71799726,"remaining_time":5.065979998},
{"learn":[0.1025979259],"iteration":824,"passed_time":23.74055234,"remaining_time":5.035874738},
{"learn":[0.1024447119],"iteration":825,"passed_time":23.76925677,"remaining_time":5.007083145},
{"learn":[0.1023126662],"iteration":826,"passed_time":23.79970041,"remaining_time":4.978655587},
{"learn":[0.1021357277],"iteration":827,"passed_time":23.82914497,"remaining_time":4.950015622},
{"learn":[0.1018739895],"iteration":828,"passed_time":23.85477534,"remaining_time":4.920586952},
{"learn":[0.1017247756],"iteration":829,"passed_time":23.8826331,"remaining_time":4.891623647},
{"learn":[0.1014259276],"iteration":830,"passed_time":23.90627929,"remaining_time":4.861806499},
{"learn":[0.1012053113],"iteration":831,"passed_time":23.93669002,"remaining_time":4.8333701},
{"learn":[0.1010633328],"iteration":832,"passed_time":23.96188056,"remaining_time":4.803882417},
{"learn":[0.1008953941],"iteration":833,"passed_time":23.9855764,"remaining_time":4.774107533},
{"learn":[0.1007328923],"iteration":834,"passed_time":24.01368209,"remaining_time":4.745218617},
{"learn":[0.1004528916],"iteration":835,"passed_time":24.03878231,"remaining_time":4.715741983},
{"learn":[0.1002993093],"iteration":836,"passed_time":24.06585765,"remaining_time":4.68666045},
{"learn":[0.1000800803],"iteration":837,"passed_time":24.09558844,"remaining_time":4.65809705},
{"learn":[0.09990569959],"iteration":838,"passed_time":24.12288507,"remaining_time":4.629063763},
{"learn":[0.09971838712],"iteration":839,"passed_time":24.14799043,"remaining_time":4.599617224},
{"learn":[0.09954834138],"iteration":840,"passed_time":24.17595387,"remaining_time":4.570721362},
{"learn":[0.09924546812],"iteration":841,"passed_time":24.20247224,"remaining_time":4.541556549},
{"learn":[0.09920641084],"iteration":842,"passed_time":24.22263561,"remaining_time":4.511214461},
{"learn":[0.09908211447],"iteration":843,"passed_time":24.24693193,"remaining_time":4.481660404},
{"learn":[0.09891930032],"iteration":844,"passed_time":24.27485829,"remaining_time":4.452784657},
{"learn":[0.09877013302],"iteration":845,"passed_time":24.29939242,"remaining_time":4.423293655},
{"learn":[0.09854789215],"iteration":846,"passed_time":24.33235932,"remaining_time":4.395337634},
{"learn":[0.09833933836],"iteration":847,"passed_time":24.35466832,"remaining_time":4.365459417},
{"learn":[0.09816316231],"iteration":848,"passed_time":24.38190427,"remaining_time":4.336475318},
{"learn":[0.09790805209],"iteration":849,"passed_time":24.41387243,"remaining_time":4.308330429},
{"learn":[0.09777202969],"iteration":850,"passed_time":24.44326804,"remaining_time":4.279726131},
{"learn":[0.09766473532],"iteration":851,"passed_time":24.46976943,"remaining_time":4.250617224},
{"learn":[0.09750698155],"iteration":852,"passed_time":24.49231845,"remaining_time":4.220833309},
{"learn":[0.09738012883],"iteration":853,"passed_time":24.51559487,"remaining_time":4.191190692},
{"learn":[0.09725911673],"iteration":854,"passed_time":24.54447076,"remaining_time":4.162512584},
{"learn":[0.09718402513],"iteration":855,"passed_time":24.57656202,"remaining_time":4.134374919},
{"learn":[0.09694317011],"iteration":856,"passed_time":24.6089303,"remaining_time":4.10627425},
{"learn":[0.09673429255],"iteration":857,"passed_time":24.63160937,"remaining_time":4.076560058},
{"learn":[0.09654328288],"iteration":858,"passed_time":24.65349667,"remaining_time":4.046732282},
{"learn":[0.09640009125],"iteration":859,"passed_time":24.68161862,"remaining_time":4.017937916},
{"learn":[0.09622045686],"iteration":860,"passed_time":24.71371968,"remaining_time":3.989787497},
{"learn":[0.09593846758],"iteration":861,"passed_time":24.74300695,"remaining_time":3.961177446},
{"learn":[0.09579234039],"iteration":862,"passed_time":24.77662771,"remaining_time":3.933253762},
{"learn":[0.09569428253],"iteration":863,"passed_time":24.80587972,"remaining_time":3.904629215},
{"learn":[0.09559993828],"iteration":864,"passed_time":24.8320976,"remaining_time":3.875529683},
{"learn":[0.0954802841],"iteration":865,"passed_time":24.8625033,"remaining_time":3.847084806},
{"learn":[0.09533332285],"iteration":866,"passed_time":24.89701171,"remaining_time":3.819264773},
{"learn":[0.09513735783],"iteration":867,"passed_time":24.92874722,"remaining_time":3.791007641},
{"learn":[0.09497964063],"iteration":868,"passed_time":24.95920179,"remaining_time":3.762549407},
{"learn":[0.09482310453],"iteration":869,"passed_time":24.98394154,"remaining_time":3.733232644},
{"learn":[0.09469579955],"iteration":870,"passed_time":25.00628825,"remaining_time":3.703571968},
{"learn":[0.09458731559],"iteration":871,"passed_time":25.04794973,"remaining_time":3.676763263},
{"learn":[0.09442792158],"iteration":872,"passed_time":25.08253136,"remaining_time":3.648890587},
{"learn":[0.09431867173],"iteration":873,"passed_time":25.11919051,"remaining_time":3.621302065},
{"learn":[0.09422121698],"iteration":874,"passed_time":25.15189857,"remaining_time":3.593128368},
{"learn":[0.09405693919],"iteration":875,"passed_time":25.19531045,"remaining_time":3.56645947},
{"learn":[0.09389529878],"iteration":876,"passed_time":25.22488042,"remaining_time":3.537811051},
{"learn":[0.0937155758],"iteration":877,"passed_time":25.25510026,"remaining_time":3.509250834},
{"learn":[0.09354874164],"iteration":878,"passed_time":25.28404938,"remaining_time":3.480511916},
{"learn":[0.09334064937],"iteration":879,"passed_time":25.31669981,"remaining_time":3.452277247},
{"learn":[0.09325467929],"iteration":880,"passed_time":25.35177236,"remaining_time":3.424359717},
{"learn":[0.09313456922],"iteration":881,"passed_time":25.38122185,"remaining_time":3.395673672},
{"learn":[0.09298891839],"iteration":882,"passed_time":25.4081518,"remaining_time":3.36665205},
{"learn":[0.09283033921],"iteration":883,"passed_time":25.43745025,"remaining_time":3.33794596},
{"learn":[0.09265601941],"iteration":884,"passed_time":25.47127033,"remaining_time":3.309826088},
{"learn":[0.09243944376],"iteration":885,"passed_time":25.5034781,"remaining_time":3.281485895},
{"learn":[0.09233782357],"iteration":886,"passed_time":25.53593162,"remaining_time":3.25316829},
{"learn":[0.092229338],"iteration":887,"passed_time":25.57743179,"remaining_time":3.225982387},
{"learn":[0.0921177131],"iteration":888,"passed_time":25.61727013,"remaining_time":3.198556788},
{"learn":[0.09193150659],"iteration":889,"passed_time":25.6520221,"remaining_time":3.170474641},
{"learn":[0.09178830231],"iteration":890,"passed_time":25.68680837,"remaining_time":3.14238172},
{"learn":[0.0916523577],"iteration":891,"passed_time":25.71307938,"remaining_time":3.113242794},
{"learn":[0.09154500996],"iteration":892,"passed_time":25.74292255,"remaining_time":3.084538313},
{"learn":[0.09139177392],"iteration":893,"passed_time":25.77576954,"remaining_time":3.056187439},
{"learn":[0.091331913],"iteration":894,"passed_time":25.80400577,"remaining_time":3.027285593},
{"learn":[0.09125664001],"iteration":895,"passed_time":25.82766692,"remaining_time":2.997854196},
{"learn":[0.09106376574],"iteration":896,"passed_time":25.8526548,"remaining_time":2.968588009},
{"learn":[0.09090407789],"iteration":897,"passed_time":25.87826199,"remaining_time":2.939401697},
{"learn":[0.09079196267],"iteration":898,"passed_time":25.90846527,"remaining_time":2.910739702},
{"learn":[0.09062990871],"iteration":899,"passed_time":25.93985256,"remaining_time":2.88220584},
{"learn":[0.09050140554],"iteration":900,"passed_time":25.96867835,"remaining_time":2.853384191},
{"learn":[0.09035357254],"iteration":901,"passed_time":25.99921204,"remaining_time":2.824748093},
{"learn":[0.09028835962],"iteration":902,"passed_time":26.02978206,"remaining_time":2.796111694},
{"learn":[0.09011620415],"iteration":903,"passed_time":26.05203496,"remaining_time":2.766587783},
{"learn":[0.08991718663],"iteration":904,"passed_time":26.0799801,"remaining_time":2.737677469},
{"learn":[0.08977526321],"iteration":905,"passed_time":26.10832936,"remaining_time":2.708811214},
{"learn":[0.08966874662],"iteration":906,"passed_time":26.13231676,"remaining_time":2.679498852},
{"learn":[0.08946712386],"iteration":907,"passed_time":26.16160919,"remaining_time":2.650735732},
{"learn":[0.08932712073],"iteration":908,"passed_time":26.18656019,"remaining_time":2.621536828},
{"learn":[0.0890881491],"iteration":909,"passed_time":26.21169844,"remaining_time":2.59236578},
{"learn":[0.08889177633],"iteration":910,"passed_time":26.24132785,"remaining_time":2.563642348},
{"learn":[0.08876562782],"iteration":911,"passed_time":26.26819309,"remaining_time":2.534650211},
{"learn":[0.08862315143],"iteration":912,"passed_time":26.29391647,"remaining_time":2.505553924},
{"learn":[0.08849735883],"iteration":913,"passed_time":26.31885706,"remaining_time":2.476391365},
{"learn":[0.08832000938],"iteration":914,"passed_time":26.35246022,"remaining_time":2.448042753},
{"learn":[0.08815170548],"iteration":915,"passed_time":26.38740687,"remaining_time":2.41980587},
{"learn":[0.08806284244],"iteration":916,"passed_time":26.41741827,"remaining_time":2.391107651},
{"learn":[0.08790573987],"iteration":917,"passed_time":26.44983174,"remaining_time":2.362621136},
{"learn":[0.08782079206],"iteration":918,"passed_time":26.47851321,"remaining_time":2.333797139},
{"learn":[0.08767388077],"iteration":919,"passed_time":26.51602705,"remaining_time":2.305741483},
{"learn":[0.08756835598],"iteration":920,"passed_time":26.54796821,"remaining_time":2.277187284},
{"learn":[0.08745751834],"iteration":921,"passed_time":26.57506308,"remaining_time":2.248215749},
{"learn":[0.0872856305],"iteration":922,"passed_time":26.60068382,"remaining_time":2.219125302},
{"learn":[0.08713968005],"iteration":923,"passed_time":26.62530713,"remaining_time":2.189960327},
{"learn":[0.08695099336],"iteration":924,"passed_time":26.65324037,"remaining_time":2.161073544},
{"learn":[0.0868217168],"iteration":925,"passed_time":26.68000738,"remaining_time":2.132095622},
{"learn":[0.08668417775],"iteration":926,"passed_time":26.70691924,"remaining_time":2.103133878},
{"learn":[0.08653858324],"iteration":927,"passed_time":26.73565588,"remaining_time":2.074318129},
{"learn":[0.08647134506],"iteration":928,"passed_time":26.76201565,"remaining_time":2.045320895},
{"learn":[0.08628715057],"iteration":929,"passed_time":26.78871334,"remaining_time":2.016354768},
{"learn":[0.08614627277],"iteration":930,"passed_time":26.81431658,"remaining_time":1.987312399},
{"learn":[0.08605732528],"iteration":931,"passed_time":26.83875895,"remaining_time":1.958192713},
{"learn":[0.08591961366],"iteration":932,"passed_time":26.86311201,"remaining_time":1.929076639},
{"learn":[0.08579719786],"iteration":933,"passed_time":26.88771941,"remaining_time":1.899988737},
{"learn":[0.08571436325],"iteration":934,"passed_time":26.91477332,"remaining_time":1.871080498},
{"learn":[0.08554585636],"iteration":935,"passed_time":26.93884623,"remaining_time":1.841972392},
{"learn":[0.0853980107],"iteration":936,"passed_time":26.97026157,"remaining_time":1.813368708},
{"learn":[0.08532642199],"iteration":937,"passed_time":26.98729847,"remaining_time":1.783808641},
{"learn":[0.08519115836],"iteration":938,"passed_time":27.00977427,"remaining_time":1.754628574},
{"learn":[0.08510434612],"iteration":939,"passed_time":27.02831472,"remaining_time":1.725211578},
{"learn":[0.08497918445],"iteration":940,"passed_time":27.04777719,"remaining_time":1.695875509},
{"learn":[0.0848739666],"iteration":941,"passed_time":27.0685859,"remaining_time":1.666643293},
{"learn":[0.08473003644],"iteration":942,"passed_time":27.08734657,"remaining_time":1.637305148},
{"learn":[0.08454251273],"iteration":943,"passed_time":27.10744235,"remaining_time":1.608068614},
{"learn":[0.08438777128],"iteration":944,"passed_time":27.13024084,"remaining_time":1.579008726},
{"learn":[0.08429441267],"iteration":945,"passed_time":27.15094065,"remaining_time":1.549842278},
{"learn":[0.08417872961],"iteration":946,"passed_time":27.17110774,"remaining_time":1.520663897},
{"learn":[0.08401210824],"iteration":947,"passed_time":27.19143287,"remaining_time":1.491513196},
{"learn":[0.08393236054],"iteration":948,"passed_time":27.21093761,"remaining_time":1.462337005},
{"learn":[0.08383322208],"iteration":949,"passed_time":27.23071933,"remaining_time":1.433195754},
{"learn":[0.08367547273],"iteration":950,"passed_time":27.25243034,"remaining_time":1.404173593},
{"learn":[0.08353282467],"iteration":951,"passed_time":27.27475154,"remaining_time":1.375197557},
{"learn":[0.08343924204],"iteration":952,"passed_time":27.29572554,"remaining_time":1.346169046},
{"learn":[0.0833537985],"iteration":953,"passed_time":27.30999434,"remaining_time":1.316834109},
{"learn":[0.08325468647],"iteration":954,"passed_time":27.32859469,"remaining_time":1.287734828},
{"learn":[0.08309776355],"iteration":955,"passed_time":27.34257562,"remaining_time":1.258444903},
{"learn":[0.08296330691],"iteration":956,"passed_time":27.363449,"remaining_time":1.229496664},
{"learn":[0.08286051706],"iteration":957,"passed_time":27.3959182,"remaining_time":1.201073658},
{"learn":[0.08271792616],"iteration":958,"passed_time":27.42654378,"remaining_time":1.172563394},
{"learn":[0.08256450346],"iteration":959,"passed_time":27.46109446,"remaining_time":1.144212269},
{"learn":[0.08249884409],"iteration":960,"passed_time":27.48643243,"remaining_time":1.115474365},
{"learn":[0.08234323666],"iteration":961,"passed_time":27.51255858,"remaining_time":1.086774663},
{"learn":[0.08225768493],"iteration":962,"passed_time":27.54370151,"remaining_time":1.058273059},
{"learn":[0.08211360181],"iteration":963,"passed_time":27.57013883,"remaining_time":1.029590247},
{"learn":[0.08203017685],"iteration":964,"passed_time":27.60394271,"remaining_time":1.001179269},
{"learn":[0.08188235811],"iteration":965,"passed_time":27.63411996,"remaining_time":0.972629481},
{"learn":[0.08173503251],"iteration":966,"passed_time":27.66190134,"remaining_time":0.9439945647},
{"learn":[0.08166298555],"iteration":967,"passed_time":27.69116507,"remaining_time":0.9154104155},
{"learn":[0.08158693856],"iteration":968,"passed_time":27.71697907,"remaining_time":0.8867145005},
{"learn":[0.08154763052],"iteration":969,"passed_time":27.74213685,"remaining_time":0.8580042324},
{"learn":[0.08139596776],"iteration":970,"passed_time":27.7710725,"remaining_time":0.8294141119},
{"learn":[0.08122163762],"iteration":971,"passed_time":27.80091591,"remaining_time":0.8008494294},
{"learn":[0.08114466549],"iteration":972,"passed_time":27.82634534,"remaining_time":0.7721596343},
{"learn":[0.08102569779],"iteration":973,"passed_time":27.8601044,"remaining_time":0.7436988855},
{"learn":[0.08094596471],"iteration":974,"passed_time":27.88715308,"remaining_time":0.7150552072},
{"learn":[0.08085586193],"iteration":975,"passed_time":27.91677825,"remaining_time":0.6864781538},
{"learn":[0.08068881753],"iteration":976,"passed_time":27.94616074,"remaining_time":0.6578932416},
{"learn":[0.08056445947],"iteration":977,"passed_time":27.97627764,"remaining_time":0.6293232189},
{"learn":[0.08050751572],"iteration":978,"passed_time":28.00205396,"remaining_time":0.6006569288},
{"learn":[0.0803910157],"iteration":979,"passed_time":28.03632133,"remaining_time":0.5721698231},
{"learn":[0.08033370154],"iteration":980,"passed_time":28.05685264,"remaining_time":0.5434048931},
{"learn":[0.08022180169],"iteration":981,"passed_time":28.08441924,"remaining_time":0.5147856887},
{"learn":[0.08012661223],"iteration":982,"passed_time":28.10640116,"remaining_time":0.4860720445},
{"learn":[0.0800411323],"iteration":983,"passed_time":28.12854192,"remaining_time":0.4573746653},
{"learn":[0.07988451844],"iteration":984,"passed_time":28.14455708,"remaining_time":0.428597316},
{"learn":[0.07982054881],"iteration":985,"passed_time":28.15984113,"remaining_time":0.3998354724},
{"learn":[0.07975681948],"iteration":986,"passed_time":28.17317674,"remaining_time":0.3710752761},
{"learn":[0.07965955455],"iteration":987,"passed_time":28.18553645,"remaining_time":0.3423344508},
{"learn":[0.07950408554],"iteration":988,"passed_time":28.19878817,"remaining_time":0.3136366732},
{"learn":[0.07941652562],"iteration":989,"passed_time":28.20978757,"remaining_time":0.2849473492},
{"learn":[0.0792877416],"iteration":990,"passed_time":28.22244421,"remaining_time":0.2563087768},
{"learn":[0.07914113364],"iteration":991,"passed_time":28.23343833,"remaining_time":0.2276890188},
{"learn":[0.07902911406],"iteration":992,"passed_time":28.24464538,"remaining_time":0.1991062615},
{"learn":[0.07891913927],"iteration":993,"passed_time":28.25670007,"remaining_time":0.1705635819},
{"learn":[0.07877215271],"iteration":994,"passed_time":28.26800409,"remaining_time":0.1420502718},
{"learn":[0.07867945163],"iteration":995,"passed_time":28.28029276,"remaining_time":0.1135754729},
{"learn":[0.07858011646],"iteration":996,"passed_time":28.29041334,"remaining_time":0.08512661987},
{"learn":[0.07853332121],"iteration":997,"passed_time":28.30097673,"remaining_time":0.05671538423},
{"learn":[0.07844279674],"iteration":998,"passed_time":28.31238254,"remaining_time":0.02834072327},
{"learn":[0.07833322586],"iteration":999,"passed_time":28.32225811,"remaining_time":0}
]}_time":0}
]}